Workbook

Sheet START HERE
A1: PROPERTY MARKETPLACE — MASTER PROJECT ROADMAP & CHECKLIST
A2: Your single source of truth for building the marketplace, from research to launch to mobile app.
A5: HOW TO USE THIS WORKBOOK EVERY DAY
A6: 1. Open MASTER ROADMAP. | B6: Look at the dashboard at the top: it tells you instantly how many tasks are done, in progress, blocked and remaining. These numbers update themselves.
A7: 2. Filter by Phase. | B7: Click the filter arrow on the 'Phase No.' column and pick the phase you are working on. Do phases roughly in order — later phases depend on earlier ones.
A8: 3. Find your next task. | B8: Filter Status = NOT STARTED and Priority = CRITICAL. Check the 'Dependency' column: if the dependency is not DONE, do that first.
A9: 4. Update Status as you go. | B9: Click any Status cell and pick from the dropdown: NOT STARTED, IN PROGRESS, BLOCKED, REVIEW, DONE, DEFERRED. The dashboard and the PHASES sheet recalculate automatically.
A10: 5. Check DECISIONS LOG weekly. | B10: Anything marked DECISION REQUIRED is waiting for you. The project cannot finish until these are answered. Write your answer in 'Final Decision' and set the date.
A12: WHAT THE COLOUR TAGS MEAN
A13: OBSERVED FROM RESEARCH | B13: This comes from the attached research document — it was actually observed on a live competitor marketplace. Treat it as evidence.
A14: PROPOSED | B14: This is a recommendation, not an observation. It is a sensible default but you may change it.
A15: DECISION REQUIRED | B15: Nobody has decided this yet. It needs YOUR answer. See the DECISIONS LOG sheet.
A16: USER REQUIREMENT | B16: This came from your own instructions rather than from the research.
A18: THE SEVEN QUESTIONS THIS WORKBOOK ANSWERS
A19: 1. What is already done? | B19: MASTER ROADMAP dashboard + filter Status = DONE.
A20: 2. What should I work on next? | B20: MASTER ROADMAP: filter Status = NOT STARTED, sort by Phase No., check Dependency.
A21: 3. What is blocked? | B21: MASTER ROADMAP: filter Status = BLOCKED.
A22: 4. What depends on what? | B22: MASTER ROADMAP 'Dependency' column, and the PHASES sheet 'Dependencies' column.
A23: 5. What belongs to the MVP? | B23: MVP CHECKLIST sheet: filter MVP? = MVP.
A24: 6. What can wait? | B24: MVP CHECKLIST: filter MVP? = FUTURE. Then see POST-LAUNCH ROADMAP for when.
A25: 7. What decisions are outstanding? | B25: DECISIONS LOG: filter Decision Status = OPEN — DECISION REQUIRED.
A27: THE SHEETS, IN THE ORDER YOU WILL NEED THEM
A28: MASTER ROADMAP | B28: All 213 tasks with dependencies, effort, deliverables and acceptance criteria. Your daily working sheet.
A29: PHASES | B29: The 24 phases at a glance, with progress bars that calculate themselves from MASTER ROADMAP.
A30: MVP CHECKLIST | B30: What must be built for launch, and what must NOT be built yet. Your defence against scope creep.
A31: FEATURE CHECKLIST | B31: Every feature broken down by who uses it and what it needs (frontend, backend, database, API).
A32: WEBSITE PAGES | B32: Every page to design and build, with its URL and whether it needs SEO.
A33: USER FLOWS | B33: Step-by-step journeys for buyers, sellers and admins, including what can go wrong at each step.
A34: DATABASE | B34: The proposed tables, what each is for, and which are MVP versus later.
A35: API CHECKLIST | B35: Every planned API endpoint. Do not build these yet — this is the plan.
A36: UI/UX CHECKLIST | B36: The design system and interface work, from tokens to accessibility.
A37: SEO CHECKLIST | B37: URL structure, metadata, sitemaps and indexation. Read this BEFORE building any page.
A38: SECURITY CHECKLIST | B38: Controls that protect users, data and the business model.
A39: TESTING & QA | B39: What to test and what 'passing' means for each item.
... A47: GLOSSARY | B47: Every technical term in plain English. Start here if a word is unfamiliar.
A49: IMPORTANT RULES BUILT INTO THIS PLAN
A50: Supply before demand. | B50: Sellers and listings come before buyer features. An empty marketplace cannot be tested by buyers.
A51: Measure before you monetise. | B51: The lead loop is fully instrumented in Phase 10, but nothing is charged until after launch. You cannot price what you cannot measure.
A52: URLs before pages. | B52: The URL structure is decided in Phase 2, before any page is built. Retrofitting SEO-grade URLs later is effectively a rewrite.
A53: Performance before launch. | B53: Speed budgets are enforced in the build pipeline before going live, because performance debt compounds.
A54: Nothing copied. | B54: This is an ORIGINAL product. No competitor branding, wording, imagery, styling or content is used anywhere.
A56: HONEST LIMITATIONS OF THIS PLAN
A57: Effort estimates assume competent full-time development. | B57: They are S (1-2 days), M (3-5 days), L (1-2 weeks), XL (2-4 weeks). If you are learning as you go, or working part-time, multiply accordingly. See DECISIONS LOG D-23.
A58: Some source research is marked UNKNOWN. | B58: The research document could not inspect the competitor's frontend code, backend or performance. Nothing here claims otherwise, and no invented technical details were used to fill gaps.
A59: One research conflict is flagged, not hidden. | B59: The research document is internally inconsistent about whether 'similar properties' belongs in the MVP. See DECISIONS LOG D-14.
A60: This plan does not include business costs. | B60: Marketing, legal fees, salaries and supply acquisition are outside this workbook's scope, but they will decide whether the project succeeds.

Sheet MASTER ROADMAP
A1: MASTER ROADMAP — complete task list, phase by phase
A2: Filter by Phase No. to see one phase at a time. Check 'Dependency' before starting a task. Update 'Status' from the dropdown — the dashboard below and the PHASES sheet recalculate automatically.
A3: PROGRESS DASHBOARD (these numbers update themselves)
A4: Total tasks | B4: =COUNTA($C$10:$C$222) -> 213 | D4: DONE | E4: =COUNTIF($J$10:$J$222,"DONE") -> 2 | G4: NOT STARTED | H4: =COUNTIF($J$10:$J$222,"NOT STARTED") -> 211
A5: IN PROGRESS | B5: =COUNTIF($J$10:$J$222,"IN PROGRESS") -> 0 | D5: BLOCKED | E5: =COUNTIF($J$10:$J$222,"BLOCKED") -> 0 | G5: REVIEW | H5: =COUNTIF($J$10:$J$222,"REVIEW") -> 0
A6: DEFERRED | B6: =COUNTIF($J$10:$J$222,"DEFERRED") -> 0 | D6: MVP tasks (Ph 0-20) | E6: =COUNTIFS($B$10:$B$222,"<=20") -> 196 | G6: Future tasks (Ph 21-23) | H6: =COUNTIFS($B$10:$B$222,">20") -> 17
A7: CRITICAL priority | B7: =COUNTIF($I$10:$I$222,"CRITICAL") -> 122 | D7: Decisions required | E7: =COUNTIF($P$10:$P$222,"DECISION REQUIRED") -> 15 | G7: OVERALL COMPLETION | H7: =IFERROR(COUNTIF($J$10:$J$222,"DONE")/COUNTA($C$10:$C$222),0) -> 0.0093896714
A9: Phase | B9: Phase No. | C9: Task ID | D9: Task | E9: Subtask | F9: Description | G9: Why It Is Needed | H9: Dependency | I9: Priority | J9: Status | K9: Owner | L9: Estimated Effort | M9: Deliverable | N9: Acceptance Criteria | O9: Notes | P9: Source
A10: Phase 0 — Research & Product Definition | B10: 0 | C10: 0.1 | D10: Competitor & market research | E10: Reverse-engineer a market leader | F10: Study the publicly observable structure, UX, URL grammar, SEO model and monetisation of an established marketplace. | G10: You cannot design an original product well without knowing what the category standard actually is. | H10: None | I10: CRITICAL | J10: DONE | K10: UNASSIGNED | L10: XL · 2–4 weeks | M10: Research specification document | N10: Document exists, every claim carries a confidence rating, sources cited. | O10: COMPLETE. See docs/99acres-reverse-engineering-and-marketplace-spec.md in this repository. | P10: OBSERVED FROM RESEARCH
A11: Phase 0 — Research & Product Definition | B11: 0 | C11: 0.2 | D11: Define the business model | E11: Confirm lead-generation model | F11: Confirm the product makes money from seller-side visibility and leads, not from buyer fees or transactions. | G11: Every downstream decision (data model, ranking, quotas) follows from this. Research confirms the incumbent monetises contact reveals. | H11: 0.1 | I11: CRITICAL | J11: DONE | K11: UNASSIGNED | L11: S · 1–2 days | M11: One-page business-model statement | N11: Written statement: who pays, for what, at which moment. | O11: Research confirms the monetisable event is the contact reveal, not the listing. | P11: OBSERVED FROM RESEARCH
A12: Phase 0 — Research & Product Definition | B12: 0 | C12: 0.3 | D12: Choose launch scope | E12: Pick cities and categories | F12: Decide which cities and which property categories the first version covers. | G12: A narrow launch is testable. A national launch across all categories is not. | H12: 0.2 | I12: CRITICAL | J12: NOT STARTED | K12: UNASSIGNED | L12: S · 1–2 days | M12: Written scope statement | N12: Named cities and categories, written down and agreed. | O12: Research proposes 3 cities, residential Buy + Rent only. YOU MUST CONFIRM which cities. See DECISIONS LOG D-11/D-12. | P12: DECISION REQUIRED
A13: Phase 0 — Research & Product Definition | B13: 0 | C13: 0.4 | D13: Define MVP boundary | E13: Agree what is NOT in v1 | F13: Write the explicit out-of-scope list so scope creep is visible when it happens. | G13: Unbounded MVPs never ship. The deferred list is as important as the included list. | H13: 0.3 | I13: CRITICAL | J13: NOT STARTED | K13: UNASSIGNED | L13: S · 1–2 days | M13: Signed-off MVP + out-of-scope list | N13: Both lists written; each deferred item has a target future phase. | O13: See MVP CHECKLIST sheet. Research §24 gives the starting boundary. | P13: OBSERVED FROM RESEARCH
A14: Phase 0 — Research & Product Definition | B14: 0 | C14: 0.5 | D14: Define success metrics | E14: Set measurable launch targets | F14: Agree the numbers that mean the MVP worked. | G14: Without targets you cannot tell success from activity. | H14: 0.4 | I14: HIGH | J14: NOT STARTED | K14: UNASSIGNED | L14: S · 1–2 days | M14: Metrics table with targets | N14: Each metric has a target number and a way to measure it. | O14: Research §24 proposes: ≥2,000 listings, search→PDP ≥25%, PDP→contact ≥8%, OTP completion ≥70%. | P14: PROPOSED
A15: Phase 0 — Research & Product Definition | B15: 0 | C15: 0.6 | D15: Legal and compliance review | E15: Engage a lawyer early | F15: Review data-protection obligations (India DPDP Act), listing liability, T&C, privacy policy, RERA advertising norms. | G15: This is not an engineering decision and getting it wrong after launch is expensive. | H15: 0.3 | I15: HIGH | J15: NOT STARTED | K15: UNASSIGNED | L15: M · 3–5 days | M15: Legal opinion + draft policies | N15: Lawyer has reviewed the data model and the T&C draft. | O15: Research §17.5 flags DPDP consent, retention, erasure; GST invoicing; RERA disclosure. Do not skip. | P15: OBSERVED FROM RESEARCH
A16: Phase 0 — Research & Product Definition | B16: 0 | C16: 0.7 | D16: Brand and naming | E16: Choose name, domain, identity | F16: Pick a product name, secure the domain and social handles, define brand direction. | G16: Needed before design, SEO and any public artefact. | H16: 0.3 | I16: HIGH | J16: NOT STARTED | K16: UNASSIGNED | L16: M · 3–5 days | M16: Name + registered domain | N16: Domain registered, name checked for trademark conflict. | O16: MUST be original. Do not reuse any competitor branding, wording or visual identity. | P16: DECISION REQUIRED
A17: Phase 0 — Research & Product Definition | B17: 0 | C17: 0.8 | D17: Supply acquisition plan | E17: Plan how to get first listings | F17: Decide how the first 2,000 listings arrive: manual outreach, agent partnerships, free posting drive. | G17: An empty marketplace cannot be tested by buyers. Supply must exist before demand. | H17: 0.3 | I17: CRITICAL | J17: NOT STARTED | K17: UNASSIGNED | L17: M · 3–5 days | M17: Written supply plan with owner | N17: A named plan with a weekly listing target. | O17: Research §23 sequencing: supply before demand. This is a business task, not an engineering task — it is the most common reason marketplaces fail. | P17: OBSERVED FROM RESEARCH
A18: Phase 1 — Project Foundation | B18: 1 | C18: 1.1 | D18: Create code repository | E18: Set up Git + GitHub | F18: Create the repository, add README, LICENSE, .gitignore and CODEOWNERS. | G18: Single source of truth for all code and history. | H18: 0.7 | I18: CRITICAL | J18: NOT STARTED | K18: UNASSIGNED | L18: S · 1–2 days | M18: Repository with initial commit | N18: Repo exists, you can clone and push. | P18: PROPOSED
A19: Phase 1 — Project Foundation | B19: 1 | C19: 1.2 | D19: Branch strategy | E19: Agree branching rules | F19: Define main/develop/feature branch rules and who can merge. | G19: Prevents broken code reaching production. | H19: 1.1 | I19: HIGH | J19: NOT STARTED | K19: UNASSIGNED | L19: S · 1–2 days | M19: Written branching policy in README | N19: Policy documented; main branch protected. | O19: PROPOSED: trunk-based with short feature branches + required PR review. | P19: PROPOSED
A20: Phase 1 — Project Foundation | B20: 1 | C20: 1.3 | D20: Choose frontend framework | E20: Confirm Next.js + TypeScript | F20: Confirm the frontend framework and language. | G20: Server-side rendering is a hard requirement for the SEO model; retrofitting it later is a rewrite. | H20: 0.4 | I20: CRITICAL | J20: NOT STARTED | K20: UNASSIGNED | L20: S · 1–2 days | M20: Recorded decision | N20: Decision written in DECISIONS LOG with date. | O20: Research §22 recommends Next.js (App Router) + React + TypeScript. See DECISIONS LOG D-01. | P20: DECISION REQUIRED
A21: Phase 1 — Project Foundation | B21: 1 | C21: 1.4 | D21: Choose backend framework | E21: Confirm backend language/framework | F21: Confirm backend framework and whether it is a modular monolith. | G21: Determines hiring, libraries and deployment for the whole project. | H21: 0.4 | I21: CRITICAL | J21: NOT STARTED | K21: UNASSIGNED | L21: S · 1–2 days | M21: Recorded decision | N21: Decision written in DECISIONS LOG with date. | O21: Research §22 recommends NestJS (TypeScript) modular monolith; Spring Boot if the team is Java-strong. See D-02. | P21: DECISION REQUIRED
A22: Phase 1 — Project Foundation | B22: 1 | C22: 1.5 | D22: Scaffold projects | E22: Create frontend + backend skeletons | F22: Create empty but runnable frontend and backend applications. | G22: Gives a working baseline everything else builds on. | H22: 1.3,1.4 | I22: CRITICAL | J22: NOT STARTED | K22: UNASSIGNED | L22: S · 1–2 days | M22: Two runnable apps | N22: Both start locally with one command. | P22: PROPOSED
A23: Phase 1 — Project Foundation | B23: 1 | C23: 1.6 | D23: Code quality tooling | E23: ESLint, Prettier, TypeScript strict | F23: Configure linting, formatting and strict type checking. | G23: Catches a large class of bugs before they are written. | H23: 1.5 | I23: HIGH | J23: NOT STARTED | K23: UNASSIGNED | L23: S · 1–2 days | M23: Lint + format config committed | N23: Lint runs clean on the scaffold. | P23: PROPOSED
A24: Phase 1 — Project Foundation | B24: 1 | C24: 1.7 | D24: Environment configuration | E24: Set up .env handling | F24: Define environment variables and a .env.example; never commit real secrets. | G24: Secrets in Git are the single most common serious security mistake. | H24: 1.5 | I24: CRITICAL | J24: NOT STARTED | K24: UNASSIGNED | L24: S · 1–2 days | M24: .env.example + secret policy | N24: No real secret exists in Git history. | O24: See SECURITY CHECKLIST and DEVOPS sheets. | P24: PROPOSED
A25: Phase 1 — Project Foundation | B25: 1 | C25: 1.8 | D25: Local development setup | E25: Docker Compose for DB + cache | F25: Run PostgreSQL and Redis locally with one command. | G25: Everyone develops against the same versions. | H25: 1.5 | I25: HIGH | J25: NOT STARTED | K25: UNASSIGNED | L25: S · 1–2 days | M25: docker-compose.yml | N25: `docker compose up` gives a working DB and cache. | P25: PROPOSED
A26: Phase 1 — Project Foundation | B26: 1 | C26: 1.9 | D26: CI pipeline (basic) | E26: GitHub Actions: lint, typecheck, test | F26: Run checks automatically on every pull request. | G26: Stops broken code merging while the codebase is still small. | H26: 1.6 | I26: HIGH | J26: NOT STARTED | K26: UNASSIGNED | L26: S · 1–2 days | M26: Green CI on the scaffold | N26: CI runs on PR and blocks merge on failure. | O26: Performance and Lighthouse gates are added later in Phase 16. | P26: PROPOSED
A27: Phase 1 — Project Foundation | B27: 1 | C27: 1.10 | D27: Project documentation | E27: Start a living README/architecture doc | F27: Document how to run, test and deploy the project. | G27: You will not remember this in three months. | H27: 1.5 | I27: MEDIUM | J27: NOT STARTED | K27: UNASSIGNED | L27: S · 1–2 days | M27: README with setup steps | N27: A new machine can run the project from the README alone. | P27: PROPOSED
A28: Phase 2 — Product Architecture | B28: 2 | C28: 2.1 | D28: Define module boundaries | E28: Agree the backend modules | F28: Split the backend into modules: identity, location, listing, search, lead, moderation, content, billing. | G28: Clear boundaries now make it cheap to split into services later, if ever needed. | H28: 1.4 | I28: CRITICAL | J28: NOT STARTED | K28: UNASSIGNED | L28: M · 3–5 days | M28: Module map diagram | N28: Every module has a written owner-of-data statement. | O28: Research §21.3 gives the module table. Modules talk via events, never by reading each other's tables. | P28: OBSERVED FROM RESEARCH
A29: Phase 2 — Product Architecture | B29: 2 | C29: 2.2 | D29: Define URL / route architecture | E29: Design the public URL structure | F29: Design every public route before building any page. | G29: The research's single highest-leverage finding: URL structure IS the product architecture for SEO. | H29: 0.3 | I29: CRITICAL | J29: NOT STARTED | K29: UNASSIGNED | L29: M · 3–5 days | M29: Route table (see WEBSITE PAGES sheet) | N29: Every planned page has an agreed final URL pattern. | O29: Research §16.5. Two surfaces: pretty SSR URLs (indexable) and /search?… (noindex). | P29: OBSERVED FROM RESEARCH
A30: Phase 2 — Product Architecture | B30: 2 | C30: 2.3 | D30: Decide rendering strategy | E30: SSR / SSG / ISR per route type | F30: Decide which pages are server-rendered, statically generated or incrementally regenerated. | G30: Directly determines SEO performance and hosting cost. | H30: 2.2 | I30: CRITICAL | J30: NOT STARTED | K30: UNASSIGNED | L30: S · 1–2 days | M30: Rendering decision per route type | N30: Each route type in WEBSITE PAGES has a rendering mode. | O30: Research §18.4: SSR for all indexable routes; personalisation must never block first paint. | P30: OBSERVED FROM RESEARCH
A31: Phase 2 — Product Architecture | B31: 2 | C31: 2.4 | D31: Choose database | E31: Confirm PostgreSQL + PostGIS | F31: Confirm the primary database and geospatial extension. | G31: One engine covers search, geo and transactions for the whole first phase. | H31: 1.4 | I31: CRITICAL | J31: NOT STARTED | K31: UNASSIGNED | L31: S · 1–2 days | M31: Recorded decision | N31: Decision in DECISIONS LOG. | O31: Research §22 recommends PostgreSQL 16 + PostGIS. See D-03. | P31: DECISION REQUIRED
A32: Phase 2 — Product Architecture | B32: 2 | C32: 2.5 | D32: Decide search approach | E32: Postgres now, OpenSearch later | F32: Confirm that MVP search runs on PostgreSQL and a search cluster is deferred. | G32: Avoids running a search cluster before there is data to justify it. | H32: 2.4 | I32: CRITICAL | J32: NOT STARTED | K32: UNASSIGNED | L32: S · 1–2 days | M32: Recorded decision + trigger | N32: Written trigger for when to migrate (listing count or latency). | O32: Research §13.3: Postgres to ~100k listings, then OpenSearch. See D-04. | P32: DECISION REQUIRED
A33: Phase 2 — Product Architecture | B33: 2 | C33: 2.6 | D33: Define the normalised filter object | E33: One filter shape for both surfaces | F33: Design a single canonical object that both the pretty URL and the query-param URL translate into. | G33: Prevents the two surfaces drifting apart and returning different results. | H33: 2.2 | I33: CRITICAL | J33: NOT STARTED | K33: UNASSIGNED | L33: M · 3–5 days | M33: Filter object schema | N33: Both URL forms parse to an identical object in tests. | O33: Research §6.2 — this is the core search design decision. | P33: OBSERVED FROM RESEARCH
A34: Phase 2 — Product Architecture | B34: 2 | C34: 2.7 | D34: Define ID strategy | E34: Public vs internal identifiers | F34: Decide how entity IDs look publicly and internally. | G34: Sequential public IDs leak business volume and allow enumeration. | H34: 2.4 | I34: HIGH | J34: NOT STARTED | K34: UNASSIGNED | L34: S · 1–2 days | M34: ID convention document | N34: Public IDs are non-sequential and prefixed per entity type. | O34: Research §11.1 observed typed prefixed IDs. PROPOSED: internal bigint + public prefixed short ID. | P34: PROPOSED
A35: Phase 2 — Product Architecture | B35: 2 | C35: 2.8 | D35: Define event/outbox pattern | E35: How modules communicate | F35: Design the transactional outbox and domain events. | G35: Keeps search index, notifications and analytics in sync without fragile dual writes. | H35: 2.1 | I35: HIGH | J35: NOT STARTED | K35: UNASSIGNED | L35: M · 3–5 days | M35: Event catalogue + outbox design | N35: Listing publish emits one event consumed by indexer and alerts. | O35: Research §21.4. | P35: OBSERVED FROM RESEARCH
A36: Phase 2 — Product Architecture | B36: 2 | C36: 2.9 | D36: Choose hosting and cloud | E36: Pick where it runs | F36: Decide hosting for frontend, backend, database and object storage. | G36: Affects cost, deployment and every DevOps task. | H36: 1.4 | I36: CRITICAL | J36: NOT STARTED | K36: UNASSIGNED | L36: S · 1–2 days | M36: Recorded decision + cost estimate | N36: Decision in DECISIONS LOG with a monthly cost estimate. | O36: Research §22: managed hosting first, Kubernetes only when justified. See D-07. | P36: DECISION REQUIRED
A37: Phase 2 — Product Architecture | B37: 2 | C37: 2.10 | D37: Write architecture document | E37: Consolidate all decisions | F37: Write one document describing the whole system. | G37: You are not an expert — this document is how you stay oriented. | H37: 2.1-2.9 | I37: HIGH | J37: NOT STARTED | K37: UNASSIGNED | L37: M · 3–5 days | M37: Architecture document | N37: A new developer can understand the system from it. | P37: PROPOSED
A38: Phase 3 — Design System & UI/UX | B38: 3 | C38: 3.1 | D38: Define design tokens | E38: Colour, type, spacing, radius scales | F38: Define the design variables that every component uses. | G38: Stops the UI drifting into inconsistency; makes dark mode and theming cheap. | H38: 1.5 | I38: CRITICAL | J38: NOT STARTED | K38: UNASSIGNED | L38: M · 3–5 days | M38: Token file (CSS variables) | N38: No component contains a raw colour or pixel value. | O38: Research §14.4/§14.5. MUST be an original visual identity — do not copy competitor colours or fonts. | P38: OBSERVED FROM RESEARCH
A39: Phase 3 — Design System & UI/UX | B39: 3 | C39: 3.2 | D39: Choose typography | E39: Font family and type scale | F39: Pick fonts, including Indic script coverage if localisation is ever planned. | G39: Font choice is hard to change later and affects performance. | H39: 3.1 | I39: HIGH | J39: NOT STARTED | K39: UNASSIGNED | L39: S · 1–2 days | M39: Type scale documented | N39: Scale defined; tabular numerals enabled for prices. | O39: Research §14.3 proposes a 1.250 scale and tabular numerals for price/area alignment. | P39: PROPOSED
A40: Phase 3 — Design System & UI/UX | B40: 3 | C40: 3.3 | D40: Build base components | E40: Button, input, select, chip, badge | F40: Build the smallest reusable UI pieces. | G40: Everything else is assembled from these. | H40: 3.1 | I40: CRITICAL | J40: NOT STARTED | K40: UNASSIGNED | L40: L · 1–2 weeks | M40: Component library v1 | N40: Each has all states: default, hover, focus, disabled, loading, error. | O40: Research §14.6. | P40: OBSERVED FROM RESEARCH
A41: Phase 3 — Design System & UI/UX | B41: 3 | C41: 3.4 | D41: Design the property card | E41: The most important component | F41: Design the card used in every result list. | G41: It is the unit of comparison; card quality drives click-through. | H41: 3.3 | I41: CRITICAL | J41: NOT STARTED | K41: UNASSIGNED | L41: M · 3–5 days | M41: Property card component | N41: Fixed image ratio, one primary action, area basis always labelled. | O41: Research §7.1. One filled primary button only — two competing buttons reduce clicks on both. | P41: OBSERVED FROM RESEARCH
A42: Phase 3 — Design System & UI/UX | B42: 3 | C42: 3.5 | D42: Design search and filter UI | E42: Search bar, filter panel, chips, sort | F42: Design the search entry point and the filter experience for desktop and mobile. | G42: Search is the product's main funnel. | H42: 3.3 | I42: CRITICAL | J42: NOT STARTED | K42: UNASSIGNED | L42: L · 1–2 weeks | M42: Search + filter components | N42: Mobile uses a full-screen sheet with a live result count on Apply. | O42: Research §6.4/§15.3. Desktop = left rail apply-on-change; mobile = sheet apply-on-confirm. | P42: OBSERVED FROM RESEARCH
A43: Phase 3 — Design System & UI/UX | B43: 3 | C43: 3.6 | D43: Design navigation | E43: Header, footer, mobile bottom nav | F43: Design site navigation for all breakpoints. | G43: Orientation and the supply-side call to action live here. | H43: 3.3 | I43: HIGH | J43: NOT STARTED | K43: UNASSIGNED | L43: M · 3–5 days | M43: Navigation components | N43: Bottom nav on mobile; Post Property visually distinct from primary actions. | O43: Research §14.9. | P43: OBSERVED FROM RESEARCH
A44: Phase 3 — Design System & UI/UX | B44: 3 | C44: 3.7 | D44: Design system states | E44: Empty, loading, error, skeleton | F44: Design what every screen shows when there is no data, data is loading, or something failed. | G44: Beginners skip these; they are half of the real user experience. | H44: 3.3 | I44: CRITICAL | J44: NOT STARTED | K44: UNASSIGNED | L44: M · 3–5 days | M44: State components | N44: Zero-results screen offers a recovery action, never a dead end. | O44: Research §4.2 empty-state rules: name the blocking filter, offer radius expansion, offer alert. | P44: OBSERVED FROM RESEARCH
A45: Phase 3 — Design System & UI/UX | B45: 3 | C45: 3.8 | D45: Accessibility baseline | E45: WCAG 2.1 AA | F45: Define and check contrast, focus rings, keyboard order, touch targets. | G45: Legal exposure, and it measurably improves usability for everyone. | H45: 3.3 | I45: HIGH | J45: NOT STARTED | K45: UNASSIGNED | L45: M · 3–5 days | M45: Accessibility checklist passed | N45: Visible focus ring everywhere; 44x44px minimum touch targets. | O45: Research §14.11. Never remove focus outlines without a replacement. | P45: OBSERVED FROM RESEARCH
A46: Phase 3 — Design System & UI/UX | B46: 3 | C46: 3.9 | D46: Responsive rules | E46: Breakpoints and layout changes | F46: Define what changes at each breakpoint. | G46: Most traffic will be mobile. | H46: 3.4,3.5 | I46: CRITICAL | J46: NOT STARTED | K46: UNASSIGNED | L46: M · 3–5 days | M46: Responsive specification | N46: Every component has a defined behaviour at each breakpoint. | O46: Research §15.2 gives the full breakpoint table. | P46: OBSERVED FROM RESEARCH
A47: Phase 3 — Design System & UI/UX | B47: 3 | C47: 3.10 | D47: Motion and reduced motion | E47: Animation rules | F47: Define durations, easing, and honour prefers-reduced-motion. | G47: Excess motion feels slow and harms accessibility. | H47: 3.3 | I47: MEDIUM | J47: NOT STARTED | K47: UNASSIGNED | L47: S · 1–2 days | M47: Motion tokens | N47: No core-path animation exceeds 200ms; reduced-motion respected. | O47: Research §14.10. | P47: OBSERVED FROM RESEARCH
A48: Phase 3 — Design System & UI/UX | B48: 3 | C48: 3.11 | D48: Wireframe key screens | E48: Home, results, PDP, posting, dashboard | F48: Draw the main screens before building them. | G48: Cheaper to change a drawing than a build. | H48: 3.4-3.7 | I48: HIGH | J48: NOT STARTED | K48: UNASSIGNED | L48: L · 1–2 weeks | M48: Wireframes for all MVP screens | N48: Every MVP page in WEBSITE PAGES has a wireframe. | P48: PROPOSED
A49: Phase 4 — Database & Backend Foundation | B49: 4 | C49: 4.1 | D49: Design database schema v1 | E49: Tables, columns, types | F49: Write the first schema covering MVP entities only. | G49: The data model constrains everything built on top of it. | H49: 2.4 | I49: CRITICAL | J49: NOT STARTED | K49: UNASSIGNED | L49: L · 1–2 weeks | M49: Schema definition / migration files | N49: All MVP tables in DATABASE sheet exist. | O49: Research §12. Do not build future-phase tables yet. | P49: OBSERVED FROM RESEARCH
A50: Phase 4 — Database & Backend Foundation | B50: 4 | C50: 4.2 | D50: Set up migrations | E50: Versioned schema changes | F50: Configure a migration tool so schema changes are versioned and reversible. | G50: Manual schema edits in production cause outages and data loss. | H50: 4.1 | I50: CRITICAL | J50: NOT STARTED | K50: UNASSIGNED | L50: S · 1–2 days | M50: Migration tooling working | N50: Migrations run forward and roll back cleanly. | P50: PROPOSED
A51: Phase 4 — Database & Backend Foundation | B51: 4 | C51: 4.3 | D51: Three area fields, not one | E51: carpet / built-up / super area | F51: Model the three Indian area measurements as separate fields. | G51: Conflating them produces wrong price-per-sqft and destroys user trust. | H51: 4.1 | I51: CRITICAL | J51: NOT STARTED | K51: UNASSIGNED | L51: S · 1–2 days | M51: Area fields in schema | N51: All three fields exist plus an explicit area-unit field. | O51: Research §12.3 — flagged as the most common data-integrity failure in this domain. | P51: OBSERVED FROM RESEARCH
A52: Phase 4 — Database & Backend Foundation | B52: 4 | C52: 4.4 | D52: Listing state machine | E52: Define lifecycle states | F52: Implement DRAFT, UNDER_SCREENING, ACTIVE, REJECTED, EXPIRED, SOLD/RENTED, DELETED. | G52: Lifecycle is a product feature, not an implementation detail. | H52: 4.1 | I52: CRITICAL | J52: NOT STARTED | K52: UNASSIGNED | L52: M · 3–5 days | M52: State machine + transitions | N52: Illegal transitions are rejected by the database or service layer. | O52: Research §8.1 observed these exact states on the incumbent. | P52: OBSERVED FROM RESEARCH
A53: Phase 4 — Database & Backend Foundation | B53: 4 | C53: 4.5 | D53: Seed reference data | E53: Property types, amenities | F53: Load the fixed lookup lists. | G53: Needed before any listing can be created. | H53: 4.1 | I53: HIGH | J53: NOT STARTED | K53: UNASSIGNED | L53: S · 1–2 days | M53: Seed scripts | N53: Reference tables populated and re-runnable. | P53: PROPOSED
A54: Phase 4 — Database & Backend Foundation | B54: 4 | C54: 4.6 | D54: Core indexes | E54: Add indexes for hot queries | F54: Add the indexes the search and dashboard queries need. | G54: Without them search degrades badly as data grows. | H54: 4.1 | I54: HIGH | J54: NOT STARTED | K54: UNASSIGNED | L54: S · 1–2 days | M54: Index migration | N54: Indexes from DATABASE sheet created. | O54: Research §12.4 gives a starting index plan. Do not add every possible index — measure first. | P54: OBSERVED FROM RESEARCH
A55: Phase 4 — Database & Backend Foundation | B55: 4 | C55: 4.7 | D55: Backend skeleton + health check | E55: Module folders, config, /health | F55: Create the backend module structure and a health endpoint. | G55: Deployment and monitoring need a health check from day one. | H55: 2.1 | I55: HIGH | J55: NOT STARTED | K55: UNASSIGNED | L55: S · 1–2 days | M55: Running API with /health | N55: /health returns 200 with DB connectivity confirmed. | P55: PROPOSED
A56: Phase 4 — Database & Backend Foundation | B56: 4 | C56: 4.8 | D56: Error handling and logging | E56: Standard error shape | F56: Define one error response format and structured logging. | G56: Consistent errors make debugging and frontend handling far simpler. | H56: 4.7 | I56: HIGH | J56: NOT STARTED | K56: UNASSIGNED | L56: S · 1–2 days | M56: Error middleware + logger | N56: All errors return the same JSON shape with a request ID. | P56: PROPOSED
A57: Phase 4 — Database & Backend Foundation | B57: 4 | C57: 4.9 | D57: API conventions | E57: Naming, versioning, pagination | F57: Agree REST conventions before writing endpoints. | G57: Inconsistent APIs are painful to consume and document. | H57: 4.7 | I57: HIGH | J57: NOT STARTED | K57: UNASSIGNED | L57: S · 1–2 days | M57: API convention document | N57: Documented and applied to the first endpoint. | O57: See API CHECKLIST sheet. | P57: PROPOSED
A58: Phase 4 — Database & Backend Foundation | B58: 4 | C58: 4.10 | D58: Object storage + presigned uploads | E58: S3-compatible bucket | F58: Set up media storage with direct-from-browser presigned uploads. | G58: Keeps large image uploads off the application server. | H58: 2.9 | I58: HIGH | J58: NOT STARTED | K58: UNASSIGNED | L58: M · 3–5 days | M58: Working upload to storage | N58: A file uploads from the browser without passing through the API. | O58: Research §22. Enforce content-type and size limits on the presigned URL. | P58: OBSERVED FROM RESEARCH
A59: Phase 4 — Database & Backend Foundation | B59: 4 | C59: 4.11 | D59: Background job queue | E59: Set up worker + queue | F59: Configure the queue and a worker process. | G59: Image processing, moderation, alerts and indexing must not block requests. | H59: 4.7 | I59: HIGH | J59: NOT STARTED | K59: UNASSIGNED | L59: M · 3–5 days | M59: Queue + worker running | N59: A test job is enqueued and processed. | O59: Research §22 proposes BullMQ on Redis to avoid new infrastructure. | P59: PROPOSED
A60: Phase 5 — User Authentication | B60: 5 | C60: 5.1 | D60: Choose OTP provider | E60: Pick an SMS/OTP vendor | F60: Select and contract an SMS provider that supports Indian DLT registration. | G60: OTP is the primary login method; DLT template registration is legally required in India and takes time. | H60: 0.6 | I60: CRITICAL | J60: NOT STARTED | K60: UNASSIGNED | L60: M · 3–5 days | M60: Signed provider + registered templates | N60: Test OTP delivered to a real Indian number. | O60: Research §22 names MSG91 / Twilio / AWS SNS as candidates. See DECISIONS LOG D-09. Start DLT registration EARLY — it has a lead time. | P60: DECISION REQUIRED
A61: Phase 5 — User Authentication | B61: 5 | C61: 5.2 | D61: User + role model | E61: Users with multiple roles | F61: Implement users where one account can be both buyer and seller. | G61: A person who buys today may sell next year; single-role accounts force duplicate accounts. | H61: 4.1 | I61: CRITICAL | J61: NOT STARTED | K61: UNASSIGNED | L61: M · 3–5 days | M61: User table + role array | N61: One account can hold buyer and owner roles simultaneously. | O61: Research §12.2. Incumbent enforces one account per phone+email. | P61: OBSERVED FROM RESEARCH
A62: Phase 5 — User Authentication | B62: 5 | C62: 5.3 | D62: OTP request + verify | E62: Send and check the code | F62: Build the endpoints that send an OTP and verify it. | G62: The entry point to every authenticated action. | H62: 5.1,5.2 | I62: CRITICAL | J62: NOT STARTED | K62: UNASSIGNED | L62: M · 3–5 days | M62: Working OTP login | N62: A new user can register and log in by phone only. | P62: OBSERVED FROM RESEARCH
A63: Phase 5 — User Authentication | B63: 5 | C63: 5.4 | D63: OTP abuse protection | E63: Rate limits and expiry | F63: Limit OTP requests per number and per IP; expire and single-use every code. | G63: Without limits, OTP endpoints are abused and your SMS bill becomes the attack. | H63: 5.3 | I63: CRITICAL | J63: NOT STARTED | K63: UNASSIGNED | L63: S · 1–2 days | M63: Rate-limit rules live | N63: Max attempts enforced; codes expire; reuse rejected. | O63: Research §17.5 proposes max 5/hour/number with exponential backoff. | P63: OBSERVED FROM RESEARCH
A64: Phase 5 — User Authentication | B64: 5 | C64: 5.5 | D64: Session tokens | E64: JWT access + refresh rotation | F64: Issue short-lived access tokens and rotating refresh tokens. | G64: Balances security against making users log in constantly. | H64: 5.3 | I64: CRITICAL | J64: NOT STARTED | K64: UNASSIGNED | L64: M · 3–5 days | M64: Token issue + refresh working | N64: Access token expires; refresh rotates; reuse is detected. | O64: Research §22. See DECISIONS LOG D-08. | P64: PROPOSED
A65: Phase 5 — User Authentication | B65: 5 | C65: 5.6 | D65: Role-based authorization | E65: Permission checks | F65: Enforce what each role may do on the server, on every endpoint. | G65: Client-side role checks are decoration; server checks are security. | H65: 5.5 | I65: CRITICAL | J65: NOT STARTED | K65: UNASSIGNED | L65: M · 3–5 days | M65: Authorization middleware | N65: A buyer token cannot edit a listing, proven by test. | P65: PROPOSED
A66: Phase 5 — User Authentication | B66: 5 | C66: 5.7 | D66: Account management | E66: Profile edit, phone change | F66: Let users update name, email and phone with re-verification. | G66: Basic expectation; phone change must invalidate sessions. | H66: 5.5 | I66: HIGH | J66: NOT STARTED | K66: UNASSIGNED | L66: M · 3–5 days | M66: Profile screens + API | N66: Phone change requires OTP and invalidates other sessions. | O66: Research §17.5. | P66: OBSERVED FROM RESEARCH
A67: Phase 5 — User Authentication | B67: 5 | C67: 5.8 | D67: Login/registration UI | E67: Auth screens and modal | F67: Build sign-in, registration and the inline auth prompt. | G67: Must interrupt a buyer action without losing what they were doing. | H67: 3.3,5.3 | I67: CRITICAL | J67: NOT STARTED | K67: UNASSIGNED | L67: M · 3–5 days | M67: Auth UI complete | N67: After login, the interrupted action (e.g. save) completes automatically. | O67: Research §9.1 — replaying the intended action after login is a real conversion factor. | P67: OBSERVED FROM RESEARCH
A68: Phase 5 — User Authentication | B68: 5 | C68: 5.9 | D68: Account deletion / data rights | E68: DPDP compliance | F68: Let users request deletion and export of their data. | G68: Legal requirement under India's data-protection law. | H68: 0.6,5.7 | I68: HIGH | J68: NOT STARTED | K68: UNASSIGNED | L68: M · 3–5 days | M68: Deletion + export flow | N68: A request is honoured within the policy window and logged. | O68: Research §17.5. Soft-delete only where leads/payments reference the user. | P68: OBSERVED FROM RESEARCH
A69: Phase 6 — Location & Property Data | B69: 6 | C69: 6.1 | D69: Design the location model | E69: Hierarchical place tree | F69: Build country → state → city → zone → locality → society as a self-referencing tree. | G69: The research calls this the most important table in the system; search, SEO and stats all depend on it. | H69: 4.1 | I69: CRITICAL | J69: NOT STARTED | K69: UNASSIGNED | L69: L · 1–2 weeks | M69: LOCATION table + tree queries | N69: Any locality resolves its full ancestor path in one query. | O69: Research §12.2/§12.3. Incumbent uses numeric location IDs shared across all features. | P69: OBSERVED FROM RESEARCH
A70: Phase 6 — Location & Property Data | B70: 6 | C70: 6.2 | D70: Source locality data | E70: Acquire place data for launch cities | F70: Obtain or compile locality names and coordinates for the launch cities. | G70: Cannot be generated; this is a real data-acquisition task people underestimate. | H70: 0.3,6.1 | I70: CRITICAL | J70: NOT STARTED | K70: UNASSIGNED | L70: L · 1–2 weeks | M70: Seeded gazetteer | N70: All localities in the launch cities exist with coordinates. | O70: DECISION REQUIRED: source (open data, commercial, manual). Research §20.4 flags boundary polygons as a genuine project. | P70: DECISION REQUIRED
A71: Phase 6 — Location & Property Data | B71: 6 | C71: 6.3 | D71: Location aliases | E71: Handle alternate names | F71: Store alternate spellings (e.g. Bangalore/Bengaluru, Gurgaon/Gurugram). | G71: Users type both; without aliases search silently fails. | H71: 6.1 | I71: HIGH | J71: NOT STARTED | K71: UNASSIGNED | L71: S · 1–2 days | M71: Alias field + search support | N71: Searching either spelling returns the same place. | O71: Research §12.2 — specifically called out for the Indian market. | P71: OBSERVED FROM RESEARCH
A72: Phase 6 — Location & Property Data | B72: 6 | C72: 6.4 | D72: Location slugs | E72: URL-safe names | F72: Generate and store stable slugs and full paths for every place. | G72: SEO URLs are built from these; they must be stable. | H72: 6.1,2.2 | I72: CRITICAL | J72: NOT STARTED | K72: UNASSIGNED | L72: S · 1–2 days | M72: Slug fields populated | N72: Every active place has a unique, stable slug. | P72: OBSERVED FROM RESEARCH
A73: Phase 6 — Location & Property Data | B73: 6 | C73: 6.5 | D73: Typeahead suggestion table | E73: Denormalised search-as-you-type data | F73: Build a separate lightweight table for autocomplete. | G73: Never run autocomplete against the live property table — it will be slow. | H73: 6.1 | I73: CRITICAL | J73: NOT STARTED | K73: UNASSIGNED | L73: M · 3–5 days | M73: place_suggest table + index | N73: Typeahead responds within the latency budget. | O73: Research §13.3. Include result counts next to suggestions — it improves selection quality. | P73: OBSERVED FROM RESEARCH
A74: Phase 6 — Location & Property Data | B74: 6 | C74: 6.6 | D74: Typeahead API + UI | E74: Multi-entity autocomplete | F74: Return grouped suggestions (city, locality, society) and render them as removable chips. | G74: Users type cities, localities and society names interchangeably. | H74: 6.5,3.5 | I74: CRITICAL | J74: NOT STARTED | K74: UNASSIGNED | L74: M · 3–5 days | M74: Working typeahead | N74: Grouped results; debounced; in-flight requests cancelled. | O74: Research §6.6. Debounce ~250ms and cancel stale requests to avoid flicker. | P74: OBSERVED FROM RESEARCH
A75: Phase 6 — Location & Property Data | B75: 6 | C75: 6.7 | D75: PostGIS geometry | E75: Coordinates and distance queries | F75: Enable PostGIS and store point geometry for places and listings. | G75: Needed for radius search, map bounds and 'near me'. | H75: 4.1 | I75: HIGH | J75: NOT STARTED | K75: UNASSIGNED | L75: M · 3–5 days | M75: Geo columns + GIST indexes | N75: A radius query returns correct results. | O75: Research §13.3. Boundary polygons can come later, city by city. | P75: OBSERVED FROM RESEARCH
A76: Phase 6 — Location & Property Data | B76: 6 | C76: 6.8 | D76: Property type taxonomy | E76: Define categories | F76: Define residential/commercial types and which fields each requires. | G76: Field sets differ per type; this drives the posting form and filters. | H76: 0.3 | I76: CRITICAL | J76: NOT STARTED | K76: UNASSIGNED | L76: M · 3–5 days | M76: Type registry | N76: Each type maps to a required field set. | O76: Research §8.2 recommends a declarative field registry rather than hardcoded forms. See D-12. | P76: OBSERVED FROM RESEARCH
A77: Phase 6 — Location & Property Data | B77: 6 | C77: 6.9 | D77: Amenity taxonomy | E77: Define amenity list and groups | F77: Define amenities grouped by society/flat/safety/recreation. | G77: Used in posting, filtering and display; changing it later is disruptive. | H77: 6.8 | I77: HIGH | J77: NOT STARTED | K77: UNASSIGNED | L77: S · 1–2 days | M77: Amenity reference data | N77: Amenities seeded with groups and filterability flags. | O77: Research §12.2. | P77: OBSERVED FROM RESEARCH
A78: Phase 7 — Seller / Owner Property Posting | B78: 7 | C78: 7.1 | D78: Design the posting wizard | E78: Plan the step sequence | F78: Design the multi-step form: basics, location, profile, media, pricing, description, contact, preview. | G78: A long single-page form has very poor completion rates on mobile. | H78: 3.11,6.8 | I78: CRITICAL | J78: NOT STARTED | K78: UNASSIGNED | L78: M · 3–5 days | M78: Wizard flow design | N78: Every step and field mapped; see USER FLOWS sheet. | O78: Research §8.1 observed a 6-step form on the incumbent; §8.2 proposes our version. | P78: OBSERVED FROM RESEARCH
A79: Phase 7 — Seller / Owner Property Posting | B79: 7 | C79: 7.2 | D79: Draft autosave | E79: Save from the first step | F79: Create a server-side draft as soon as the user starts, and save each step. | G79: Losing a half-finished form is the single biggest abandonment cause. | H79: 7.1,5.5 | I79: CRITICAL | J79: NOT STARTED | K79: UNASSIGNED | L79: M · 3–5 days | M79: Draft persistence | N79: Refreshing mid-form loses nothing; draft resumable from dashboard. | O79: Research §8.2 flags this as a critical requirement. | P79: OBSERVED FROM RESEARCH
A80: Phase 7 — Seller / Owner Property Posting | B80: 7 | C80: 7.3 | D80: Config-driven form fields | E80: Declarative field registry | F80: Drive the visible fields from (intent, segment, property type) configuration. | G80: Hardcoded branching becomes unmaintainable once there are several property types. | H80: 6.8,7.1 | I80: HIGH | J80: NOT STARTED | K80: UNASSIGNED | L80: L · 1–2 weeks | M80: Field registry + renderer | N80: Adding a property type needs no new form code. | O80: Research §8.2. | P80: OBSERVED FROM RESEARCH
A81: Phase 7 — Seller / Owner Property Posting | B81: 7 | C81: 7.4 | D81: Location step | E81: Map pin + locality validation | F81: Let the seller pick locality and drag a map pin; validate the pin against the locality. | G81: Wrong locations make search results wrong and erode trust fast. | H81: 6.6,6.7 | I81: CRITICAL | J81: NOT STARTED | K81: UNASSIGNED | L81: M · 3–5 days | M81: Location step working | N81: Pin outside the selected locality triggers a warning. | O81: Research §8.2. | P81: OBSERVED FROM RESEARCH
A82: Phase 7 — Seller / Owner Property Posting | B82: 7 | C82: 7.5 | D82: Photo upload | E82: Multi-image upload pipeline | F82: Client-side compression, presigned upload, progress, reorder, set primary. | G82: Photos are the highest-impact listing field. | H82: 4.10,7.1 | I82: CRITICAL | J82: NOT STARTED | K82: UNASSIGNED | L82: L · 1–2 weeks | M82: Working photo upload | N82: Multiple photos upload, reorder and persist reliably on mobile. | O82: Research §24 proposes a conservative cap of 30 for MVP (incumbent allows 50). | P82: OBSERVED FROM RESEARCH
A83: Phase 7 — Seller / Owner Property Posting | B83: 7 | C83: 7.6 | D83: Image processing worker | E83: Thumbnails, format conversion, EXIF strip | F83: Generate sized variants, convert to modern formats, strip EXIF metadata. | G83: EXIF can contain the home's GPS coordinates — a real privacy risk. | H83: 4.11,7.5 | I83: CRITICAL | J83: NOT STARTED | K83: UNASSIGNED | L83: M · 3–5 days | M83: Processing pipeline | N83: Variants generated; EXIF removed; originals retained securely. | O83: Research §17.5 and §18.4. | P83: OBSERVED FROM RESEARCH
A84: Phase 7 — Seller / Owner Property Posting | B84: 7 | C84: 7.7 | D84: Perceptual image hashing | E84: Duplicate detection groundwork | F84: Compute and store an image fingerprint on upload. | G84: Duplicate listings are the top user complaint in this category; build the hook early. | H84: 7.6 | I84: HIGH | J84: NOT STARTED | K84: UNASSIGNED | L84: M · 3–5 days | M84: phash stored per image | N84: Identical images across listings are detectable by query. | O84: Research §12.2/§17.5 — 'build the hash pipeline early, tune later'. | P84: OBSERVED FROM RESEARCH
A85: Phase 7 — Seller / Owner Property Posting | B85: 7 | C85: 7.8 | D85: Pricing step | E85: Price, negotiable, deposits, charges | F85: Capture sale price or rent plus deposit, maintenance and charges. | G85: Price is the primary comparison field; incomplete pricing generates wasted leads. | H85: 7.1 | I85: CRITICAL | J85: NOT STARTED | K85: UNASSIGNED | L85: M · 3–5 days | M85: Pricing step working | N85: Rent listings capture deposit and maintenance separately. | P85: OBSERVED FROM RESEARCH
A86: Phase 7 — Seller / Owner Property Posting | B86: 7 | C86: 7.9 | D86: Description sanitisation | E86: Strip contact details from text | F86: Detect and remove phone numbers, emails and URLs from free text, including obfuscated forms. | G86: Protects the lead model and prevents off-platform scams. | H86: 7.1 | I86: CRITICAL | J86: NOT STARTED | K86: UNASSIGNED | L86: M · 3–5 days | M86: Sanitisation active | N86: Obfuscated numbers ('nine eight seven…') are caught in tests. | O86: Research §17.4 — incumbent enforces this in both text and images. | P86: OBSERVED FROM RESEARCH
A87: Phase 7 — Seller / Owner Property Posting | B87: 7 | C87: 7.10 | D87: Completeness score | E87: Live listing quality score | F87: Show a score with the value of each missing field. | G87: The cheapest available lever on listing quality. | H87: 7.3 | I87: HIGH | J87: NOT STARTED | K87: UNASSIGNED | L87: M · 3–5 days | M87: Score shown in wizard | N87: Score updates live and names the next best field to add. | O87: Research §8.2. | P87: OBSERVED FROM RESEARCH
A88: Phase 7 — Seller / Owner Property Posting | B88: 7 | C88: 7.11 | D88: Preview step | E88: Exact public rendering | F88: Show the seller precisely what buyers will see. | G88: Builds seller confidence and catches mistakes before publication. | H88: 7.3,9.1 | I88: HIGH | J88: NOT STARTED | K88: UNASSIGNED | L88: M · 3–5 days | M88: Preview screen | N88: Preview is visually identical to the live page. | P88: OBSERVED FROM RESEARCH
A89: Phase 7 — Seller / Owner Property Posting | B89: 7 | C89: 7.12 | D89: Publish + free quota | E89: Submit for screening, enforce limits | F89: Publish into the screening state and enforce the free-listing quota. | G89: Quota is the foundation of later monetisation. | H89: 7.11,4.4 | I89: CRITICAL | J89: NOT STARTED | K89: UNASSIGNED | L89: M · 3–5 days | M89: Publish working | N89: Quota enforced; over-quota attempt is blocked with a clear message. | O89: Research §8.1 observed 1–2 free owner listings. Our quota value: DECISION REQUIRED. | P89: DECISION REQUIRED
A90: Phase 7 — Seller / Owner Property Posting | B90: 7 | C90: 7.13 | D90: Edit / renew / delete | E90: Manage an existing listing | F90: Let sellers edit, renew before expiry and delete listings. | G90: Stale listings are the category's biggest trust problem. | H90: 7.12 | I90: HIGH | J90: NOT STARTED | K90: UNASSIGNED | L90: M · 3–5 days | M90: Listing management working | N90: Edited listings re-enter screening where materially changed. | P90: OBSERVED FROM RESEARCH
A91: Phase 8 — Property Search & Filters | B91: 8 | C91: 8.1 | D91: Search query builder | E91: Translate filters to SQL | F91: Build the service that turns the normalised filter object into a database query. | G91: The core of the product; everything funnels through it. | H91: 2.6,4.6 | I91: CRITICAL | J91: NOT STARTED | K91: UNASSIGNED | L91: L · 1–2 weeks | M91: Search service | N91: All MVP filters combine correctly and return correct results. | O91: Research §6.3 gives the full filter taxonomy. | P91: OBSERVED FROM RESEARCH
A92: Phase 8 — Property Search & Filters | B92: 8 | C92: 8.2 | D92: Facet counts | E92: Counts per filter option | F92: Compute how many results each filter option would return. | G92: Counts appear in titles, buttons and labels; wrong counts look broken. | H92: 8.1 | I92: CRITICAL | J92: NOT STARTED | K92: UNASSIGNED | L92: L · 1–2 weeks | M92: Facet count service | N92: Counts exclude the facet's own selection (standard faceted semantics). | O92: Research §6.4 rule 3 — getting this wrong makes multi-select appear broken. | P92: OBSERVED FROM RESEARCH
A93: Phase 8 — Property Search & Filters | B93: 8 | C93: 8.3 | D93: Sorting | E93: Relevance, price, newest | F93: Implement sort orders. | G93: Users distrust results that ignore an explicit sort. | H93: 8.1 | I93: CRITICAL | J93: NOT STARTED | K93: UNASSIGNED | L93: M · 3–5 days | M93: Sort working | N93: Explicit sorts are pure — promoted listings never interleave. | O93: Research §13.5 rule 2. | P93: OBSERVED FROM RESEARCH
A94: Phase 8 — Property Search & Filters | B94: 8 | C94: 8.4 | D94: Relevance ranking v1 | E94: Deterministic scoring | F94: Score by match quality, freshness and listing completeness. | G94: Machine learning needs traffic; start with rules you can explain. | H94: 8.3 | I94: HIGH | J94: NOT STARTED | K94: UNASSIGNED | L94: M · 3–5 days | M94: Ranking function | N94: Ranking is documented and reproducible. | O94: Research §13.5 gives the formula. No paid boost exists yet in MVP. | P94: OBSERVED FROM RESEARCH
A95: Phase 8 — Property Search & Filters | B95: 8 | C95: 8.5 | D95: Results page (SEO surface) | E95: Server-rendered landing pages | F95: Build the indexable results page at pretty URLs. | G95: This is the main customer-acquisition channel. | H95: 8.1,2.3,3.4 | I95: CRITICAL | J95: NOT STARTED | K95: UNASSIGNED | L95: L · 1–2 weeks | M95: Landing page route | N95: Page renders server-side with correct H1, count and content. | O95: Research §4.2/§16. | P95: OBSERVED FROM RESEARCH
A96: Phase 8 — Property Search & Filters | B96: 8 | C96: 8.6 | D96: Results page (app surface) | E96: Interactive filtered search | F96: Build the /search interface with live filtering. | G96: Different job from the SEO page: state, speed, no page reloads. | H96: 8.5 | I96: CRITICAL | J96: NOT STARTED | K96: UNASSIGNED | L96: L · 1–2 weeks | M96: Interactive search | N96: Filter change updates URL and results without losing scroll. | O96: Research §6.4 rules 5 and 6. Must be noindex. | P96: OBSERVED FROM RESEARCH
A97: Phase 8 — Property Search & Filters | B97: 8 | C97: 8.7 | D97: Filter state never lost | E97: State preservation rules | F97: Guarantee filters, scroll and results survive every interaction and error. | G97: The incumbent's users specifically complain that filtering throws them back to home. | H97: 8.6 | I97: CRITICAL | J97: NOT STARTED | K97: UNASSIGNED | L97: M · 3–5 days | M97: State tests passing | N97: No filter or sort action can navigate away or clear state, even on API error. | O97: Research §18.2 — this is our clearest differentiation opportunity. | P97: OBSERVED FROM RESEARCH
A98: Phase 8 — Property Search & Filters | B98: 8 | C98: 8.8 | D98: Applied filter chips | E98: Removable chips in plain language | F98: Show applied filters as chips with human-readable labels. | G98: Users must see and undo what they applied. | H98: 8.6 | I98: HIGH | J98: NOT STARTED | K98: UNASSIGNED | L98: S · 1–2 days | M98: Chips working | N98: Chips read '₹40L–₹60L', not raw parameter values. | O98: Research §6.4 rule 7. | P98: OBSERVED FROM RESEARCH
A99: Phase 8 — Property Search & Filters | B99: 8 | C99: 8.9 | D99: Pagination (two kinds) | E99: Path pages + infinite scroll | F99: Path-based pages for crawlers, infinite scroll for the app surface. | G99: The research found the incumbent deliberately runs both. | H99: 8.5,8.6 | I99: CRITICAL | J99: NOT STARTED | K99: UNASSIGNED | L99: M · 3–5 days | M99: Both pagination modes | N99: Crawlable /page/2 exists; app surface scrolls without breaking the footer. | O99: Research §2.1/§6.1. | P99: OBSERVED FROM RESEARCH
A100: Phase 8 — Property Search & Filters | B100: 8 | C100: 8.10 | D100: Non-linear range sliders | E100: Budget and area controls | F100: Make sliders denser where most inventory sits, with exact numeric inputs. | G100: A linear 0–10cr slider makes the common 40–60L range untouchable. | H100: 3.5,8.6 | I100: HIGH | J100: NOT STARTED | K100: UNASSIGNED | L100: M · 3–5 days | M100: Range controls | N100: The dense band is selectable precisely; numeric entry also works. | O100: Research §6.4 rule 8. | P100: OBSERVED FROM RESEARCH
A101: Phase 8 — Property Search & Filters | B101: 8 | C101: 8.11 | D101: Zero-result recovery | E101: Relaxation ladder | F101: When nothing matches, widen budget, then radius, then config — and say so. | G101: Property searches are over-constrained constantly. | H101: 8.1,3.7 | I101: HIGH | J101: NOT STARTED | K101: UNASSIGNED | L101: M · 3–5 days | M101: Relaxation working | N101: User is told what was relaxed and can undo it in one tap. | O101: Research §13.6. | P101: OBSERVED FROM RESEARCH
...

Sheet PHASES
A1: PHASES — the whole project at a glance
A2: Progress is calculated automatically from the MASTER ROADMAP sheet. Do the phases roughly in order: later phases depend on earlier ones.
A4: Phase No. | B4: Phase Name | C4: Objective | D4: Main Deliverables | E4: Dependencies | F4: Estimated Duration | G4: Status | H4: Completion %
A5: 0 | B5: Phase 0 — Research & Product Definition | C5: Understand the market and decide exactly what to build. | D5: Research spec; business-model statement; launch scope; MVP boundary; success metrics; legal review; supply plan | E5: None | F5: 2–3 weeks | G5: =IF($H5>=1,"DONE",IF($H5>0,"IN PROGRESS","NOT STARTED")) -> IN PROGRESS | H5: =IFERROR(COUNTIFS('MASTER ROADMAP'!$B$10:$B$222,$A5,'MASTER ROADMAP'!$J$10:$J$222,"DONE")/COUNTIFS('MASTER ROADMAP'!$B$10:$B$222,$A5),0) -> 0.25
A6: 1 | B6: Phase 1 — Project Foundation | C6: Get a working, version-controlled, automatically-checked codebase. | D6: Repository; branch policy; scaffolds; linting; CI; local Docker setup | E6: Phase 0 | F6: 1–2 weeks | G6: =IF($H6>=1,"DONE",IF($H6>0,"IN PROGRESS","NOT STARTED")) -> NOT STARTED | H6: =IFERROR(COUNTIFS('MASTER ROADMAP'!$B$10:$B$222,$A6,'MASTER ROADMAP'!$J$10:$J$222,"DONE")/COUNTIFS('MASTER ROADMAP'!$B$10:$B$222,$A6),0) -> 0
A7: 2 | B7: Phase 2 — Product Architecture | C7: Decide the shape of the system before building any of it. | D7: Module map; URL architecture; rendering strategy; filter object; ID strategy; architecture document | E7: Phase 1 | F7: 1–2 weeks | G7: =IF($H7>=1,"DONE",IF($H7>0,"IN PROGRESS","NOT STARTED")) -> NOT STARTED | H7: =IFERROR(COUNTIFS('MASTER ROADMAP'!$B$10:$B$222,$A7,'MASTER ROADMAP'!$J$10:$J$222,"DONE")/COUNTIFS('MASTER ROADMAP'!$B$10:$B$222,$A7),0) -> 0
A8: 3 | B8: Phase 3 — Design System & UI/UX | C8: Build an original, consistent, accessible visual language. | D8: Design tokens; component library; property card; search UI; states; responsive rules; wireframes | E8: Phase 1 | F8: 3–4 weeks | G8: =IF($H8>=1,"DONE",IF($H8>0,"IN PROGRESS","NOT STARTED")) -> NOT STARTED | H8: =IFERROR(COUNTIFS('MASTER ROADMAP'!$B$10:$B$222,$A8,'MASTER ROADMAP'!$J$10:$J$222,"DONE")/COUNTIFS('MASTER ROADMAP'!$B$10:$B$222,$A8),0) -> 0
A9: 4 | B9: Phase 4 — Database & Backend Foundation | C9: Create the data model and the backend skeleton. | D9: Schema v1; migrations; seed data; indexes; API conventions; object storage; job queue | E9: Phase 2 | F9: 2–3 weeks | G9: =IF($H9>=1,"DONE",IF($H9>0,"IN PROGRESS","NOT STARTED")) -> NOT STARTED | H9: =IFERROR(COUNTIFS('MASTER ROADMAP'!$B$10:$B$222,$A9,'MASTER ROADMAP'!$J$10:$J$222,"DONE")/COUNTIFS('MASTER ROADMAP'!$B$10:$B$222,$A9),0) -> 0
A10: 5 | B10: Phase 5 — User Authentication | C10: Let people register and log in securely by phone. | D10: OTP login; sessions; roles; authorization; profile; account deletion | E10: Phase 4 | F10: 2 weeks | G10: =IF($H10>=1,"DONE",IF($H10>0,"IN PROGRESS","NOT STARTED")) -> NOT STARTED | H10: =IFERROR(COUNTIFS('MASTER ROADMAP'!$B$10:$B$222,$A10,'MASTER ROADMAP'!$J$10:$J$222,"DONE")/COUNTIFS('MASTER ROADMAP'!$B$10:$B$222,$A10),0) -> 0
A11: 6 | B11: Phase 6 — Location & Property Data | C11: Build the place hierarchy everything else depends on. | D11: Gazetteer; aliases; slugs; typeahead; PostGIS; property-type and amenity taxonomies | E11: Phase 4 | F11: 2–3 weeks | G11: =IF($H11>=1,"DONE",IF($H11>0,"IN PROGRESS","NOT STARTED")) -> NOT STARTED | H11: =IFERROR(COUNTIFS('MASTER ROADMAP'!$B$10:$B$222,$A11,'MASTER ROADMAP'!$J$10:$J$222,"DONE")/COUNTIFS('MASTER ROADMAP'!$B$10:$B$222,$A11),0) -> 0
A12: 7 | B12: Phase 7 — Seller / Owner Property Posting | C12: Let an owner list a property from a phone in under 8 minutes. | D12: Posting wizard; autosave; media pipeline; sanitisation; completeness score; publish + quota | E12: Phases 5, 6 | F12: 3–4 weeks | G12: =IF($H12>=1,"DONE",IF($H12>0,"IN PROGRESS","NOT STARTED")) -> NOT STARTED | H12: =IFERROR(COUNTIFS('MASTER ROADMAP'!$B$10:$B$222,$A12,'MASTER ROADMAP'!$J$10:$J$222,"DONE")/COUNTIFS('MASTER ROADMAP'!$B$10:$B$222,$A12),0) -> 0
A13: 8 | B13: Phase 8 — Property Search & Filters | C13: Let buyers find what they want, fast, without losing state. | D13: Search service; facets; sorting; ranking; both result surfaces; pagination; zero-result recovery | E13: Phases 6, 7 | F13: 3–4 weeks | G13: =IF($H13>=1,"DONE",IF($H13>0,"IN PROGRESS","NOT STARTED")) -> NOT STARTED | H13: =IFERROR(COUNTIFS('MASTER ROADMAP'!$B$10:$B$222,$A13,'MASTER ROADMAP'!$J$10:$J$222,"DONE")/COUNTIFS('MASTER ROADMAP'!$B$10:$B$222,$A13),0) -> 0
A14: 9 | B14: Phase 9 — Property Detail Page | C14: Answer the buyer's questions and lead them to contact. | D14: PDP; gallery; sticky contact; details; static map; seller card; save | E14: Phases 3, 8 | F14: 2–3 weeks | G14: =IF($H14>=1,"DONE",IF($H14>0,"IN PROGRESS","NOT STARTED")) -> NOT STARTED | H14: =IFERROR(COUNTIFS('MASTER ROADMAP'!$B$10:$B$222,$A14,'MASTER ROADMAP'!$J$10:$J$222,"DONE")/COUNTIFS('MASTER ROADMAP'!$B$10:$B$222,$A14),0) -> 0
A15: 10 | B15: Phase 10 — Leads / Enquiry / Contact Reveal | C15: Close the loop: deliver a measured lead to the seller. | D15: Inquiry model; enquiry form; OTP reveal; dedupe; rate limits; lead inbox; notifications; funnel events | E15: Phases 5, 9 | F15: 2–3 weeks | G15: =IF($H15>=1,"DONE",IF($H15>0,"IN PROGRESS","NOT STARTED")) -> NOT STARTED | H15: =IFERROR(COUNTIFS('MASTER ROADMAP'!$B$10:$B$222,$A15,'MASTER ROADMAP'!$J$10:$J$222,"DONE")/COUNTIFS('MASTER ROADMAP'!$B$10:$B$222,$A15),0) -> 0
A16: 11 | B16: Phase 11 — User Dashboard | C16: Give both sides a home base. | D16: Dashboard shell; my listings; saved properties; listing analytics; notification preferences | E16: Phases 7, 10 | F16: 1–2 weeks | G16: =IF($H16>=1,"DONE",IF($H16>0,"IN PROGRESS","NOT STARTED")) -> NOT STARTED | H16: =IFERROR(COUNTIFS('MASTER ROADMAP'!$B$10:$B$222,$A16,'MASTER ROADMAP'!$J$10:$J$222,"DONE")/COUNTIFS('MASTER ROADMAP'!$B$10:$B$222,$A16),0) -> 0
... A28: 23 | B28: Phase 23 — Native Mobile App | C28: Build native apps only if the data justifies them. | D28: Technology decision; mobile design; buyer journey; posting + verification; store release; release process | E28: Phase 22 | F28: 8–12 weeks | G28: =IF($H28>=1,"DONE",IF($H28>0,"IN PROGRESS","NOT STARTED")) -> NOT STARTED | H28: =IFERROR(COUNTIFS('MASTER ROADMAP'!$B$10:$B$222,$A28,'MASTER ROADMAP'!$J$10:$J$222,"DONE")/COUNTIFS('MASTER ROADMAP'!$B$10:$B$222,$A28),0) -> 0

Sheet MVP CHECKLIST
A1: MVP CHECKLIST — what to build now, and what NOT to build yet
A2: Filter MVP? = MVP for launch scope. Filter MVP? = FUTURE to see what is deliberately deferred and when it returns. This sheet is your defence against scope creep.
A4: Feature | B4: Category | C4: MVP? | D4: Priority | E4: Reason | F4: Dependencies | G4: Status | H4: Future Phase | I4: Source
A5: Intent tabs (Buy / Rent) | B5: Search | C5: MVP | D5: CRITICAL | E5: Buy and Rent are different products with different filters and economics; separating them is foundational. | F5: Phase 6 | G5: NOT STARTED | H5: — | I5: OBSERVED FROM RESEARCH
A6: Multi-select location typeahead | B6: Search | C6: MVP | D6: CRITICAL | E6: Real users search several localities at once; the entire funnel starts here. | F6: Gazetteer (6.1) | G6: NOT STARTED | H6: — | I6: OBSERVED FROM RESEARCH
A7: Faceted filters (budget, BHK, type, area, furnishing, status, posted-by, verified) | B7: Search | C7: MVP | D7: CRITICAL | E7: Core of the product. Research §6.3 defines the full set. | F7: Phase 8 | G7: NOT STARTED | H7: — | I7: OBSERVED FROM RESEARCH
A8: Sorting (relevance, price up/down, newest) | B8: Search | C8: MVP | D8: CRITICAL | E8: Users distrust results that ignore an explicit sort. | F8: Phase 8 | G8: NOT STARTED | H8: — | I8: OBSERVED FROM RESEARCH
A9: Filter state never lost on change or error | B9: Search | C9: MVP | D9: CRITICAL | E9: The incumbent's most-complained-about failure. This is our differentiator. | F9: Phase 8 | G9: NOT STARTED | H9: — | I9: OBSERVED FROM RESEARCH
A10: Result cards | B10: Property | C10: MVP | D10: CRITICAL | E10: The unit of comparison; drives click-through. | F10: Phase 3 | G10: NOT STARTED | H10: — | I10: OBSERVED FROM RESEARCH
A11: SEO landing pages with path pagination | B11: SEO | C11: MVP | D11: CRITICAL | E11: Primary acquisition channel; cannot be retrofitted. | F11: Phase 14 | G11: NOT STARTED | H11: — | I11: OBSERVED FROM RESEARCH
A12: Property detail page | B12: Property | C12: MVP | D12: CRITICAL | E12: Where the decision and the lead happen. | F12: Phase 9 | G12: NOT STARTED | H12: — | I12: OBSERVED FROM RESEARCH
A13: Image gallery | B13: Property | C13: MVP | D13: CRITICAL | E13: Photos are the most-used element on the page. | F13: Phase 9 | G13: NOT STARTED | H13: — | I13: OBSERVED FROM RESEARCH
A14: Static location map on the detail page | B14: Property | C14: MVP | D14: HIGH | E14: Location is the primary decision factor. NOTE: this is a static map, NOT interactive map search. | F14: Phase 6, 9 | G14: NOT STARTED | H14: — | I14: OBSERVED FROM RESEARCH
A15: Save / shortlist | B15: Buyer | C15: MVP | D15: CRITICAL | E15: Primary retention action in a months-long decision. | F15: Phase 9 | G15: NOT STARTED | H15: — | I15: OBSERVED FROM RESEARCH
... A63: Community Q&A / editorial engine | B63: Content | C63: FUTURE | D63: LOW | E63: Long-tail SEO value but high ongoing editorial cost. | F63: Phase 14 | G63: NOT STARTED | H63: v2.0 | I63: OBSERVED FROM RESEARCH

Sheet FEATURE CHECKLIST
A1: FEATURE CHECKLIST — every feature, and what it needs to be built
A2: Grouped by who uses it. 'Frontend / Backend / Database / API / Third-party' tell you which parts of the system each feature touches.
A4: Feature | B4: User Type | C4: Description | D4: MVP/Future | E4: Frontend | F4: Backend | G4: Database | H4: API | I4: Third-party service | J4: Dependency | K4: Status | L4: Source
A5: Browse by intent (Buy/Rent) | B5: Buyer | C5: Switch the whole search context between buying and renting. | D5: MVP | E5: Yes | F5: Yes | G5: PROPERTY | H5: GET /search | I5: — | J5: Phase 6 | K5: NOT STARTED | L5: OBSERVED FROM RESEARCH
A6: Location typeahead | B6: Buyer | C6: Search-as-you-type across cities, localities and societies. | D6: MVP | E6: Yes | F6: Yes | G6: LOCATION, PLACE_SUGGEST | H6: GET /places/suggest | I6: — | J6: Gazetteer | K6: NOT STARTED | L6: OBSERVED FROM RESEARCH
A7: Faceted search | B7: Buyer | C7: Filter results across many dimensions with live counts. | D7: MVP | E7: Yes | F7: Yes | G7: PROPERTY, LOCATION | H7: GET /search, GET /search/facets | I7: — | J7: Phase 8 | K7: NOT STARTED | L7: OBSERVED FROM RESEARCH
A8: Sort results | B8: Buyer | C8: Order results by relevance, price or recency. | D8: MVP | E8: Yes | F8: Yes | G8: PROPERTY | H8: GET /search | I8: — | J8: Phase 8 | K8: NOT STARTED | L8: OBSERVED FROM RESEARCH
A9: Infinite scroll results | B9: Buyer | C9: Load more results as the user scrolls on the app surface. | D9: MVP | E9: Yes | F9: Yes | G9: PROPERTY | H9: GET /search?page= | I9: — | J9: Phase 8 | K9: NOT STARTED | L9: OBSERVED FROM RESEARCH
A10: Crawlable paginated pages | B10: Buyer | C10: Path-based result pages that search engines can index. | D10: MVP | E10: Yes | F10: Yes | G10: PROPERTY | H10: SSR route | I10: — | J10: Phase 14 | K10: NOT STARTED | L10: OBSERVED FROM RESEARCH
A11: Property detail view | B11: Buyer | C11: Full listing information on one page. | D11: MVP | E11: Yes | F11: Yes | G11: PROPERTY, PROPERTY_MEDIA, AMENITY | H11: GET /properties/{id} | I11: — | J11: Phase 9 | K11: NOT STARTED | L11: OBSERVED FROM RESEARCH
A12: Image gallery | B12: Buyer | C12: Browse listing photos including full-screen view. | D12: MVP | E12: Yes | F12: No | G12: PROPERTY_MEDIA | H12: included in PDP | I12: CDN | J12: Phase 9 | K12: NOT STARTED | L12: OBSERVED FROM RESEARCH
A13: Static location map | B13: Buyer | C13: See where the property is on a map. | D13: MVP | E13: Yes | F13: No | G13: PROPERTY (geo) | H13: included in PDP | I13: Maps provider | J13: D-06 | K13: NOT STARTED | L13: OBSERVED FROM RESEARCH
A14: Save / shortlist | B14: Buyer | C14: Keep a list of properties to revisit. | D14: MVP | E14: Yes | F14: Yes | G14: FAVORITE | H14: POST/DELETE /favorites | I14: — | J14: Phase 5, 9 | K14: NOT STARTED | L14: OBSERVED FROM RESEARCH
A15: Send enquiry | B15: Buyer | C15: Message the seller about a listing. | D15: MVP | E15: Yes | F15: Yes | G15: INQUIRY | H15: POST /inquiries | I15: — | J15: Phase 10 | K15: NOT STARTED | L15: OBSERVED FROM RESEARCH
... A73: EMI calculator | B73: Content | C73: Estimate monthly loan payments. | D73: FUTURE | E73: Yes | F73: No | G73: — | H73: client-side | I73: — | J73: v2.2 | K73: NOT STARTED | L73: OBSERVED FROM RESEARCH

Sheet WEBSITE PAGES
A1: WEBSITE PAGES — every page to design and build
A2: URL patterns follow the SEO architecture proposed in the research. Decide these URLs in Phase 2, BEFORE building any page — changing them after launch costs search ranking.
A4: Page name | B4: URL pattern | C4: Purpose | D4: User type | E4: SEO required? | F4: Dynamic/Static | G4: Required components | H4: API/data required | I4: Mobile required? | J4: Status | K4: Source
A5: Homepage | B5: / | C5: Route the visitor into a typed intent plus a place, as fast as possible. | D5: All | E5: Yes | F5: Dynamic (SSR + cached) | G5: Header, intent tabs, hero search, quick chips, recommended rail, budget tiles, locality cards, owner CTA, SEO footer | H5: Suggest API, popular localities, recommended listings | I5: Yes | J5: NOT STARTED | K5: OBSERVED FROM RESEARCH
A6: Search results — SEO landing | B6: /{intent}/{city}[/{locality}][/{filter-slug}] | C6: Indexable landing page for a specific search intent; the main acquisition channel. | D6: Buyer/Tenant | E6: Yes | F6: Dynamic (SSR + ISR) | G6: Breadcrumb, H1 with count, filter rail, sort, chips, result cards, pagination, SEO copy, internal links, FAQ | H6: Search API, facet counts, internal link clusters | I6: Yes | J6: NOT STARTED | K6: OBSERVED FROM RESEARCH
A7: Search results — paginated | B7: /{intent}/{city}/.../page/{n} | C7: Crawlable deep pages so inventory beyond page 1 can be indexed. | D7: Buyer/Tenant | E7: Yes | F7: Dynamic (SSR) | G7: Same as landing page plus prev/next links | H7: Search API with offset | I7: Yes | J7: NOT STARTED | K7: OBSERVED FROM RESEARCH
A8: Search — interactive app surface | B8: /search?… | C8: Fast, stateful filtering without page reloads. Deliberately NOT indexed. | D8: Buyer/Tenant | E8: No (noindex) | F8: Dynamic (client + API) | G8: Filter panel/sheet, chips, sort, infinite scroll, result count | H8: Search API, facet API | I8: Yes | J8: NOT STARTED | K8: OBSERVED FROM RESEARCH
A9: Property detail | B9: /property/{slug}-p{id} | C9: Answer every buyer question and convert to a lead. | D9: Buyer/Tenant | E9: Yes | F9: Dynamic (SSR) | G9: Breadcrumb, gallery, header, sticky contact, details grid, amenities, map, seller card, similar, FAQ, JSON-LD | H9: Property API, similar API, locality summary | I9: Yes | J9: NOT STARTED | K9: OBSERVED FROM RESEARCH
A10: Property expired | B10: /property/{slug}-p{id} (HTTP 410) | C10: Handle a removed listing without a dead end or an SEO penalty. | D10: Buyer/Tenant | E10: Yes (410) | F10: Dynamic (SSR) | G10: Explanation, similar active listings, search CTA | H10: Similar listings API | I10: Yes | J10: NOT STARTED | K10: OBSERVED FROM RESEARCH
A11: Locality hub | B11: /localities/{city}/{locality} | C11: Capture research-intent traffic and link into listings. | D11: Buyer/Tenant | E11: Yes | F11: Dynamic (SSR + ISR) | G11: Locality summary, listing rails by intent, nearby localities, map, stats | H11: Locality API, listing counts | I11: Yes | J11: NOT STARTED | K11: OBSERVED FROM RESEARCH
A12: City hub | B12: /localities/{city} | C12: Top-level geographic entry point and crawl distribution. | D12: Buyer/Tenant | E12: Yes | F12: Dynamic (SSR + ISR) | G12: Locality grid, popular searches, listing counts | H12: Locality API | I12: Yes | J12: NOT STARTED | K12: OBSERVED FROM RESEARCH
A13: Login / Register | B13: /login, /register | C13: Let users authenticate by phone OTP. | D13: All | E13: No (noindex) | F13: Dynamic | G13: Phone input, OTP input, role select, resend timer | H13: Auth API | I13: Yes | J13: NOT STARTED | K13: OBSERVED FROM RESEARCH
A14: Post property wizard | B14: /post-property | C14: Let a seller create a listing in under 8 minutes on a phone. | D14: Seller/Owner/Agent | E14: No (noindex) | F14: Dynamic | G14: Stepper, config-driven fields, map pin, uploader, completeness score, preview | H14: Listings API, media presign, places API | I14: Yes | J14: NOT STARTED | K14: OBSERVED FROM RESEARCH
A15: Post property landing | B15: /post-property-free | C15: Marketing page that converts owners into sellers. | D15: Seller/Owner | E15: Yes | F15: Static/ISR | G15: Value proposition, steps explainer, CTA, FAQ | H15: None | I15: Yes | J15: NOT STARTED | K15: PROPOSED
... A45: EMI calculator | B45: /home-loan/emi-calculator | C45: High-intent finance tool and SEO asset. DEFERRED to v2.2. | D45: Buyer | E45: Yes | F45: Static + client JS | G45: Calculator, results, related content | H45: None | I45: Yes | J45: NOT STARTED | K45: OBSERVED FROM RESEARCH

Sheet USER FLOWS
A1: USER FLOWS — step-by-step journeys, including what can go wrong
A2: Fifteen complete journeys for buyers, sellers and admins. The 'Possible Error' column is the most valuable part: these are the failures to design for and test.
A4: Flow | B4: Step No. | C4: Actor | D4: Action | E4: Screen | F4: System Response | G4: Next Step | H4: Possible Error | I4: Status
A5: A. Buyer searches for a property | B5: 1 | C5: Buyer | D5: Opens the site | E5: Homepage | F5: Homepage renders server-side with the search widget ready | G5: Step 2 | H5: Slow first load — must stay within the LCP budget | I5: NOT STARTED
A6: A. Buyer searches for a property | B6: 2 | C6: Buyer | D6: Chooses the Buy or Rent tab | E6: Homepage | F6: Search form reconfigures for the chosen intent | G6: Step 3 | H6: Wrong filter set shown if intent not applied | I6: NOT STARTED
A7: A. Buyer searches for a property | B7: 3 | C7: Buyer | D7: Types a city or locality name | E7: Homepage | F7: Typeahead returns grouped suggestions with result counts | G7: Step 4 | H7: No suggestions if the gazetteer lacks the place; stale results if requests are not cancelled | I7: NOT STARTED
A8: A. Buyer searches for a property | B8: 4 | C8: Buyer | D8: Selects one or more places | E8: Homepage | F8: Each selection becomes a removable chip | G8: Step 5 | H8: Duplicate chips if not de-duplicated | I8: NOT STARTED
A9: A. Buyer searches for a property | B9: 5 | C9: Buyer | D9: Presses Search | E9: Homepage | F9: Navigates to the SEO landing URL for that intent and place | G9: Step 6 | H9: Unknown place cannot resolve to a URL | I9: NOT STARTED
A10: A. Buyer searches for a property | B10: 6 | C10: System | D10: Renders results | E10: Search results | F10: Server-rendered results with count in H1 and title | G10: Flow B | H10: Zero results — must show the recovery ladder, never a blank page | I10: NOT STARTED
A11: B. Buyer filters results | B11: 1 | C11: Buyer | D11: Opens filters | E11: Search results (desktop rail / mobile sheet) | F11: Filter panel opens showing option counts | G11: Step 2 | H11: Counts wrong if facet semantics are incorrect | I11: NOT STARTED
A12: B. Buyer filters results | B12: 2 | C12: Buyer | D12: Sets a budget range | E12: Filter panel | F12: Result count preview updates live | G12: Step 3 | H12: Linear slider makes the common range unselectable | I12: NOT STARTED
A13: B. Buyer filters results | B13: 3 | C13: Buyer | D13: Selects BHK and property type | E13: Filter panel | F13: Counts for other facets recalculate | G13: Step 4 | H13: Zero-count options hidden instead of disabled — looks broken | I13: NOT STARTED
A14: B. Buyer filters results | B14: 4 | C14: Buyer | D14: Applies filters | E14: Filter panel | F14: URL updates; results refresh; chips appear | G14: Step 5 | H14: CRITICAL: must never navigate away, reset scroll or clear state | I14: NOT STARTED
A15: B. Buyer filters results | B15: 5 | C15: Buyer | D15: Changes sort order | E15: Search results | F15: Results reorder; explicit sort is respected exactly | G15: Step 6 | H15: Promoted listings interleaving into an explicit sort destroys trust | I15: NOT STARTED
A16: B. Buyer filters results | B16: 6 | C16: Buyer | D16: Removes a filter chip | E16: Search results | F16: That filter is removed and results refresh | G16: Flow C | H16: Back button behaviour inconsistent if history is mismanaged | I16: NOT STARTED
... A74: O. Admin handles a reported listing | B74: 5 | C74: System | D74: Closes the loop | E74: — | F74: Reporter informed; seller informed if action was taken | G74: End | H74: Reporter never hearing back, so stops reporting | I74: NOT STARTED

Sheet DATABASE
A1: DATABASE — proposed tables and what each one is for
A2: An ORIGINAL conceptual schema derived from the observed functionality. Build only the MVP tables first. 'PostGIS?' marks tables needing map/location capability.
A4: Table | B4: Purpose | C4: Important Fields | D4: Relationships | E4: Indexes | F4: PostGIS? | G4: MVP/Future | H4: Status | I4: Source
A5: USER | B5: Every person on the platform: buyer, seller, agent, builder or admin. | C5: id, public_id, phone (unique, verified_at), email, name, roles[], status, preferred_city_id, created_at, deleted_at | D5: 1:1 AGENT_PROFILE / BUILDER_PROFILE; 1:N PROPERTY, INQUIRY, FAVORITE | E5: phone (unique), email (unique), status | F5: No | G5: MVP | H5: NOT STARTED | I5: OBSERVED FROM RESEARCH
A6: AGENT_PROFILE | B6: Extra details for users acting as agents. | C6: user_id, agency_name, slug, rera_agent_id, verified_status, areas_served[], rating, response_rate | D6: 1:1 USER | E6: user_id (unique), slug (unique) | F6: No | G6: FUTURE (v1.4) | H6: NOT STARTED | I6: OBSERVED FROM RESEARCH
A7: BUILDER_PROFILE | B7: Extra details for developer accounts. | C7: user_id, name, slug, logo_media_id, established_year, rera_ids[], verified_status | D7: 1:1 USER; 1:N PROJECT | E7: user_id (unique), slug (unique) | F7: No | G7: FUTURE (v1.5) | H7: NOT STARTED | I7: OBSERVED FROM RESEARCH
A8: LOCATION | B8: The place hierarchy: country, state, city, zone, locality, society. The most important table in the system. | C8: id, public_id, parent_id, type, name, slug, full_slug, centroid, boundary, pincode, aliases[], listing_count, is_active | D8: Self-referencing tree; 1:N PROPERTY | E8: parent_id+type+is_active, slug, GIST(centroid), GIST(boundary) | F8: YES | G8: MVP | H8: NOT STARTED | I8: OBSERVED FROM RESEARCH
A9: PROPERTY | B9: A listing. The central fact table. | C9: id, public_id, slug, owner_user_id, posted_by, intent, segment, property_type_id, location_id, geo, geo_precision, bedrooms, bathrooms, carpet_area, builtup_area, super_area, area_unit, price, status, is_verified, completeness_score, published_at, expires_at | D9: N:1 USER, LOCATION, PROPERTY_TYPE; 1:N PROPERTY_MEDIA, INQUIRY, PRICE_HISTORY; M:N AMENITY | E9: (status,intent,segment,location_id,price) WHERE ACTIVE; GIST(geo); (published_at DESC); (owner_user_id,status) | F9: YES | G9: MVP | H9: NOT STARTED | I9: OBSERVED FROM RESEARCH
A10: PROPERTY_MEDIA | B10: Photos, videos and floor plans for a listing. One table with a kind discriminator. | C10: id, property_id, kind, storage_key, cdn_url, width, height, sort_order, is_primary, phash, moderation_status | D10: N:1 PROPERTY | E10: (property_id, sort_order), phash | F10: No | G10: MVP | H10: NOT STARTED | I10: OBSERVED FROM RESEARCH
A11: PROPERTY_TYPE | B11: Reference list of property types and the fields each requires. | C11: id, code, name, segment, required_fields[], is_active | D11: 1:N PROPERTY | E11: code (unique) | F11: No | G11: MVP | H11: NOT STARTED | I11: OBSERVED FROM RESEARCH
A12: AMENITY | B12: Reference list of amenities, grouped and filterable. | C12: id, code, name, category, applies_to_segments[], is_filterable, sort_order | D12: M:N PROPERTY via PROPERTY_AMENITY | E12: code (unique) | F12: No | G12: MVP | H12: NOT STARTED | I12: OBSERVED FROM RESEARCH
A13: PROPERTY_AMENITY | B13: Join table linking listings to amenities, with an optional value. | C13: property_id, amenity_id, value | D13: N:N join | E13: (property_id), (amenity_id) | F13: No | G13: MVP | H13: NOT STARTED | I13: OBSERVED FROM RESEARCH
A14: INQUIRY | B14: A lead. The monetisable event — model it explicitly from day one. | C14: id, property_id, from_user_id, to_user_id, type (QUERY/CONTACT_VIEW/CALLBACK/VISIT), contact_snapshot, source_surface, is_billable, dedupe_key, seller_status, seller_notes, created_at | D14: N:1 PROPERTY, USER (from and to) | E14: (to_user_id, created_at DESC), dedupe_key (UNIQUE) | F14: No | G14: MVP | H14: NOT STARTED | I14: OBSERVED FROM RESEARCH
A15: FAVORITE | B15: A buyer's saved listing. | C15: user_id, property_id, created_at, note | D15: N:N USER-PROPERTY | E15: PK (user_id, property_id), (property_id) | F15: No | G15: MVP | H15: NOT STARTED | I15: OBSERVED FROM RESEARCH
... A36: OUTBOX | B36: Transactional outbox so events are published reliably. | C36: id, aggregate_type, aggregate_id, event_type, payload, published_at, created_at | D36: — | E36: (published_at NULLS FIRST, created_at) | F36: No | G36: MVP | H36: NOT STARTED | I36: OBSERVED FROM RESEARCH

Sheet API CHECKLIST
A1: API CHECKLIST — the planned endpoints (do NOT build these yet)
A2: This is the plan, not an instruction to start coding. 'Error Cases' matter as much as the success path — they are what makes an API feel reliable.
A4: API ID | B4: Module | C4: Method | D4: Endpoint | E4: Purpose | F4: Authentication | G4: Request | H4: Response | I4: Error Cases | J4: Database Tables | K4: MVP/Future | L4: Status
A5: API-01 | B5: Auth | C5: POST | D5: /auth/otp/request | E5: Send a one-time code to a phone number. | F5: Public | G5: {phone, purpose} | H5: {challenge_id, expires_in} | I5: 429 rate limited; 400 invalid phone; 503 SMS provider down | J5: OTP_CHALLENGE | K5: MVP | L5: NOT STARTED
A6: API-02 | B6: Auth | C6: POST | D6: /auth/otp/verify | E6: Verify the code and issue a session. | F6: Public | G6: {challenge_id, code} | H6: {access_token, refresh_token, user} | I6: 400 wrong code; 410 expired; 429 too many attempts | J6: OTP_CHALLENGE, USER, SESSION | K6: MVP | L6: NOT STARTED
A7: API-03 | B7: Auth | C7: POST | D7: /auth/refresh | E7: Exchange a refresh token for a new access token. | F7: Refresh token | G7: {refresh_token} | H7: {access_token, refresh_token} | I7: 401 invalid; 403 reuse detected (revoke all) | J7: SESSION | K7: MVP | L7: NOT STARTED
A8: API-04 | B8: Auth | C8: POST | D8: /auth/logout | E8: End the current session. | F8: Bearer | G8: {} | H8: 204 | I8: 401 unauthenticated | J8: SESSION | K8: MVP | L8: NOT STARTED
A9: API-05 | B9: User | C9: GET | D9: /me | E9: Return the signed-in user's profile. | F9: Bearer | G9: — | H9: {user} | I9: 401 | J9: USER | K9: MVP | L9: NOT STARTED
A10: API-06 | B10: User | C10: PATCH | D10: /me | E10: Update profile details. | F10: Bearer | G10: {name, email} | H10: {user} | I10: 400 validation; 409 email taken | J10: USER | K10: MVP | L10: NOT STARTED
A11: API-07 | B11: User | C11: POST | D11: /me/phone/change | E11: Change phone number with re-verification. | F11: Bearer | G11: {new_phone, challenge_id, code} | H11: {user} | I11: 400; 409 number in use | J11: USER, OTP_CHALLENGE, SESSION | K11: MVP | L11: NOT STARTED
A12: API-08 | B12: User | C12: POST | D12: /me/delete | E12: Request account deletion (data-protection right). | F12: Bearer | G12: {reason} | H12: {request_id, effective_at} | I12: 401; 409 active obligations | J12: USER | K12: MVP | L12: NOT STARTED
A13: API-09 | B13: Places | C13: GET | D13: /places/suggest | E13: Autocomplete cities, localities and societies. | F13: Public | G13: ?q=&limit=&city_id= | H13: [{id, type, label, path, listing_count}] | I13: 400 query too short | J13: PLACE_SUGGEST | K13: MVP | L13: NOT STARTED
A14: API-10 | B14: Places | C14: GET | D14: /places/{id} | E14: Return a place and its ancestors. | F14: Public | G14: — | H14: {place, ancestors[]} | I14: 404 | J14: LOCATION | K14: MVP | L14: NOT STARTED
A15: API-11 | B15: Search | C15: GET | D15: /search | E15: Return filtered, sorted, paginated listings. | F15: Public | G15: Normalised filter params + sort + page | H15: {results[], total, page, facets_summary} | I15: 400 invalid filter; 422 unknown place | J15: PROPERTY, LOCATION | K15: MVP | L15: NOT STARTED
... A54: API-50 | B54: Health | C54: GET | D54: /health | E54: Liveness and dependency check for monitoring. | F54: Public | G54: — | H54: {status, db, cache, version} | I54: 503 dependency down | J54: — | K54: MVP | L54: NOT STARTED

Sheet UI-UX CHECKLIST
A1: UI/UX CHECKLIST — design system and interface work
A2: The design system must be ORIGINAL. Extract principles from the research, never the competitor's colours, fonts or visual identity.
A4: Area | B4: Item | C4: What To Build | D4: Why It Matters | E4: MVP/Future | F4: Status | G4: Source
A5: Design system | B5: Design tokens | C5: Define colour, spacing, radius and elevation as named variables. | D5: Stops the interface drifting into inconsistency; makes dark mode cheap later. | E5: MVP | F5: NOT STARTED | G5: OBSERVED FROM RESEARCH
A6: Design system | B6: Original visual identity | C6: Create a colour palette and identity that is entirely your own. | D6: Copying a competitor's trade dress is the one part of this project with real legal exposure. | E6: MVP | F6: NOT STARTED | G6: OBSERVED FROM RESEARCH
A7: Typography | B7: Font family | C7: Choose one UI font with Indic script coverage if localisation is ever planned. | D7: Font changes late are disruptive and affect performance. | E7: MVP | F7: NOT STARTED | G7: OBSERVED FROM RESEARCH
A8: Typography | B8: Type scale | C8: Adopt a consistent scale (e.g. 12/14/16/18/20/25/31/39/49). | D8: Arbitrary font sizes make a UI look amateur. | E8: MVP | F8: NOT STARTED | G8: OBSERVED FROM RESEARCH
A9: Typography | B9: Tabular numerals | C9: Enable tabular figures for price, area and statistics. | D9: Numbers in lists must align to be comparable at a glance. | E9: MVP | F9: NOT STARTED | G9: OBSERVED FROM RESEARCH
A10: Colour | B10: Semantic tokens | C10: Name colours by role (primary, trust, danger) not by hue. | D10: Lets you change the palette without touching components. | E10: MVP | F10: NOT STARTED | G10: OBSERVED FROM RESEARCH
A11: Colour | B11: Contrast compliance | C11: Meet WCAG AA contrast on all text. | D11: Legal requirement and readability on phones in daylight. | E11: MVP | F11: NOT STARTED | G11: OBSERVED FROM RESEARCH
A12: Colour | B12: Never colour alone | C12: Pair every colour-coded meaning with an icon or text. | D12: Colour-blind users cannot decode colour-only signals. | E12: MVP | F12: NOT STARTED | G12: OBSERVED FROM RESEARCH
A13: Colour | B13: Dark mode tokens | C13: Define the dark palette from the start, even if shipped later. | D13: Retrofitting dark mode is far harder than planning for it. | E13: FUTURE | F13: NOT STARTED | G13: OBSERVED FROM RESEARCH
A14: Spacing | B14: 4px spacing scale | C14: Use 4/8/12/16/24/32/48/64 only. | D14: Consistent rhythm is most of what makes a UI feel designed. | E14: MVP | F14: NOT STARTED | G14: OBSERVED FROM RESEARCH
A15: Spacing | B15: Grid and containers | C15: Define container widths and column counts per breakpoint. | D15: Keeps layouts predictable across pages. | E15: MVP | F15: NOT STARTED | G15: OBSERVED FROM RESEARCH
... A72: Motion | B72: No hover dependencies | C72: Nothing reachable only by hover. | D72: Touch devices have no hover. | E72: MVP | F72: NOT STARTED | G72: OBSERVED FROM RESEARCH

Sheet SEO CHECKLIST
A1: SEO CHECKLIST — how people will find the site
A2: Read this BEFORE building any page. URL structure and rendering decisions cannot be retrofitted cheaply. 'LATER' items are the programmatic scale-up after launch.
A4: Area | B4: Item | C4: What To Do | D4: Why It Matters | E4: MVP/Later | F4: Status | G4: Source
A5: URL architecture | B5: Design routes before building | C5: Agree every public URL pattern in Phase 2. | D5: Retrofitting SEO-grade URLs onto a finished app is effectively a rewrite. | E5: MVP | F5: NOT STARTED | G5: OBSERVED FROM RESEARCH
A6: URL architecture | B6: Keyword-rich readable slugs | C6: Put intent, config, type and place into the URL. | D6: Observed on the incumbent; the slug carries the query terms users type. | E6: MVP | F6: NOT STARTED | G6: OBSERVED FROM RESEARCH
A7: URL architecture | B7: Typed ID suffix | C7: Append a short typed ID to detail URLs (e.g. -p12345). | D7: Guarantees uniqueness so slugs can be regenerated without breaking links. | E7: MVP | F7: NOT STARTED | G7: OBSERVED FROM RESEARCH
A8: URL architecture | B8: Two separate surfaces | C8: Pretty SSR URLs are indexable; /search query URLs are not. | D8: Keeps indexation controlled while still offering an app-like experience. | E8: MVP | F8: NOT STARTED | G8: OBSERVED FROM RESEARCH
A9: URL architecture | B9: Avoid subdomains | C9: Keep builders, projects and agents on the main domain as paths. | D9: Subdomains split authority and complicate analytics and sessions. | E9: MVP | F9: NOT STARTED | G9: OBSERVED FROM RESEARCH
A10: Canonical URLs | B10: Canonical on every page | C10: Point each filtered variant to its cleanest indexable form. | D10: Prevents duplicate-content dilution across thousands of combinations. | E10: MVP | F10: NOT STARTED | G10: OBSERVED FROM RESEARCH
A11: Canonical URLs | B11: Self-canonical on detail pages | C11: Each listing canonicalises to itself. | D11: Avoids accidental consolidation onto the wrong URL. | E11: MVP | F11: NOT STARTED | G11: OBSERVED FROM RESEARCH
A12: Index strategy | B12: Allowlist indexable facets | C12: Only named filter combinations may be indexed. | D12: Uncontrolled facet indexation is the classic cause of portal demotion. | E12: MVP | F12: NOT STARTED | G12: OBSERVED FROM RESEARCH
A13: Index strategy | B13: noindex the app surface | C13: The interactive /search route must not be indexed. | D13: It duplicates the landing pages with unstable parameters. | E13: MVP | F13: NOT STARTED | G13: OBSERVED FROM RESEARCH
A14: Thin content | B14: Minimum inventory gate | C14: Only index a page above an inventory threshold. | D14: Thousands of near-empty pages are a liability, not an asset. | E14: MVP | F14: NOT STARTED | G14: OBSERVED FROM RESEARCH
A15: Thin content | B15: Redirect below-threshold pages | C15: Send them to the parent page with nearby inventory shown. | D15: Preserves the user experience without indexing an empty page. | E15: MVP | F15: NOT STARTED | G15: OBSERVED FROM RESEARCH
... A51: Hreflang | B51: Multi-language tags | C51: Only if multi-language is ever built. | D51: Not applicable to a single-language launch. | E51: FUTURE | F51: NOT STARTED | G51: PROPOSED

Sheet SECURITY CHECKLIST
A1: SECURITY CHECKLIST — protecting users, data and the business model
A2: Every CRITICAL item must be DONE before launch. Nothing here involves bypassing anyone else's security — these are controls for YOUR system.
A4: Area | B4: Control | C4: What To Do | D4: Why It Matters | E4: Priority | F4: Status | G4: Source
A5: Authentication | B5: OTP as primary login | C5: Phone-based one-time codes as the main login method. | D5: Appropriate for the Indian market where phone is the primary identity. | E5: CRITICAL | F5: NOT STARTED | G5: OBSERVED FROM RESEARCH
A6: Authentication | B6: Hash OTP codes at rest | C6: Store a hash of the code, never the code itself. | D6: A database leak must not expose live codes. | E6: CRITICAL | F6: NOT STARTED | G6: PROPOSED
A7: Authentication | B7: Single-use codes | C7: Consume the code on first successful use. | D7: Prevents replay of an intercepted code. | E7: CRITICAL | F7: NOT STARTED | G7: OBSERVED FROM RESEARCH
A8: Authentication | B8: Short expiry | C8: Expire codes within a few minutes. | D8: Limits the window for interception. | E8: CRITICAL | F8: NOT STARTED | G8: OBSERVED FROM RESEARCH
A9: Authentication | B9: Attempt limits | C9: Lock the challenge after a small number of wrong attempts. | D9: Prevents brute-forcing a 6-digit code. | E9: CRITICAL | F9: NOT STARTED | G9: OBSERVED FROM RESEARCH
A10: OTP security | B10: Per-number rate limits | C10: Cap OTP requests per phone number per hour. | D10: Without this your SMS bill becomes the attack surface. | E10: CRITICAL | F10: NOT STARTED | G10: OBSERVED FROM RESEARCH
A11: OTP security | B11: Per-IP rate limits | C11: Cap OTP requests per IP address. | D11: Stops distributed abuse from one source. | E11: CRITICAL | F11: NOT STARTED | G11: OBSERVED FROM RESEARCH
A12: OTP security | B12: Exponential backoff | C12: Increase the delay after each repeated request. | D12: Makes automated abuse uneconomic. | E12: HIGH | F12: NOT STARTED | G12: OBSERVED FROM RESEARCH
A13: OTP security | B13: Monitor spend | C13: Alert on abnormal SMS volume. | D13: Detects abuse before the bill arrives. | E13: HIGH | F13: NOT STARTED | G13: PROPOSED
A14: Authorization | B14: Server-side checks on every endpoint | C14: Never rely on the client hiding a button. | D14: Client-side role checks are decoration, not security. | E14: CRITICAL | F14: NOT STARTED | G14: OBSERVED FROM RESEARCH
A15: Authorization | B15: Object-level ownership checks | C15: Verify the requester owns the listing or lead they are acting on. | D15: Broken object-level access control is the most common serious API flaw. | E15: CRITICAL | F15: NOT STARTED | G15: OBSERVED FROM RESEARCH
... A64: Review | B64: Dependency vulnerability scanning | C64: Automate scanning of third-party packages. | D64: Most vulnerabilities arrive through dependencies. | E64: HIGH | F64: NOT STARTED | G64: PROPOSED

Sheet TESTING & QA
A1: TESTING & QA — what to test and what 'passing' means
A2: Every row has a concrete acceptance criterion. If you cannot tell whether it passed, the criterion is not specific enough.
A4: Test Area | B4: Test Type | C4: What To Test | D4: Acceptance Criteria | E4: MVP/Future | F4: Status | G4: Source
A5: Strategy | B5: Planning | C5: Decide the mix of unit, integration and end-to-end tests. | D5: A written test strategy exists and is followed in CI. | E5: MVP | F5: NOT STARTED | G5: PROPOSED
A6: Business logic | B6: Unit | C6: Quota calculation, price formatting, area conversion, completeness score. | D6: All core calculations covered; edge cases (zero, negative, very large) included. | E6: MVP | F6: NOT STARTED | G6: PROPOSED
A7: Business logic | B7: Unit | C7: Listing state machine transitions. | D7: Every legal transition passes; every illegal transition is rejected. | E7: MVP | F7: NOT STARTED | G7: PROPOSED
A8: Business logic | B8: Unit | C8: Filter object normalisation from both URL forms. | D8: Pretty URL and query URL produce an identical filter object. | E8: MVP | F8: NOT STARTED | G8: OBSERVED FROM RESEARCH
A9: Business logic | B9: Unit | C9: Relevance ranking function. | D9: Ranking is deterministic and reproducible for a fixed input set. | E9: MVP | F9: NOT STARTED | G9: PROPOSED
A10: Authentication | B10: Integration | C10: OTP request, verify, expiry, reuse and attempt limits. | D10: Expired and reused codes are rejected; limits enforced. | E10: MVP | F10: NOT STARTED | G10: OBSERVED FROM RESEARCH
A11: Authentication | B11: Integration | C11: Token refresh and refresh-token reuse detection. | D11: Reuse of a rotated refresh token revokes the session family. | E11: MVP | F11: NOT STARTED | G11: PROPOSED
A12: Authentication | B12: Integration | C12: Phone change invalidates other sessions. | D12: Old sessions cannot act after a phone change. | E12: MVP | F12: NOT STARTED | G12: OBSERVED FROM RESEARCH
A13: Authorization | B13: Integration | C13: Cross-role access attempts on every endpoint. | D13: A buyer token cannot read or modify another user's listings or leads. | E13: MVP | F13: NOT STARTED | G13: OBSERVED FROM RESEARCH
A14: Authorization | B14: Integration | C14: Object ownership checks. | D14: User A cannot edit user B's listing by guessing an ID. | E14: MVP | F14: NOT STARTED | G14: OBSERVED FROM RESEARCH
A15: Property posting | B15: E2E | C15: Complete the wizard end to end on a mobile viewport. | D15: Listing created, screened and published successfully. | E15: MVP | F15: NOT STARTED | G15: OBSERVED FROM RESEARCH
... A64: Regression | B64: Automated | C64: Full suite runs on every main-branch build. | D64: Suite is green before any production deploy. | E64: MVP | F64: NOT STARTED | G64: PROPOSED

Sheet PERFORMANCE
A1: PERFORMANCE — hard speed targets
A2: These budgets come from the research document. Measure on a throttled mid-range Android on simulated 4G, never on a developer laptop. Being measurably faster than the incumbent is this product's clearest differentiator.
A4: Metric | B4: What It Means (plain English) | C4: Target | D4: Hard Fail | E4: How To Measure | F4: Status | G4: Source
A5: LCP — Largest Contentful Paint (mobile, p75) | B5: How long until the biggest thing on screen appears. The main 'does this feel fast' number. | C5: <= 2.0 s | D5: > 2.5 s | E5: Lighthouse in CI + real user monitoring, throttled mid-range Android on simulated 4G | F5: NOT STARTED | G5: OBSERVED FROM RESEARCH
A6: CLS — Cumulative Layout Shift | B6: How much the page jumps around while loading. Zero is ideal. | C6: <= 0.05 | D6: > 0.1 | E6: Lighthouse + RUM; check result cards and the image gallery specifically | F6: NOT STARTED | G6: OBSERVED FROM RESEARCH
A7: INP — Interaction to Next Paint | B7: How quickly the page responds when you tap or click something. | C7: <= 150 ms | D7: > 200 ms | E7: RUM in the field; test filter and sort interactions specifically | F7: NOT STARTED | G7: OBSERVED FROM RESEARCH
A8: TTFB — Time To First Byte (SSR, p75) | B8: How long the server takes to start sending the page. | C8: <= 400 ms | D8: > 800 ms | E8: Server timing headers + RUM; measure landing pages and detail pages | F8: NOT STARTED | G8: OBSERVED FROM RESEARCH
A9: JavaScript transferred (search route) | B9: How much code the browser downloads for the search page. | C9: <= 180 KB gzip | D9: > 250 KB | E9: Bundle analyser in CI; fail the build on breach | F9: NOT STARTED | G9: OBSERVED FROM RESEARCH
A10: CSS transferred | B10: How much styling code is downloaded. | C10: <= 40 KB gzip | D10: > 60 KB | E10: Bundle analyser in CI | F10: NOT STARTED | G10: OBSERVED FROM RESEARCH
A11: Image bytes above the fold | B11: Weight of images visible before scrolling. Usually the biggest cost. | C11: <= 150 KB | D11: > 250 KB | E11: Lighthouse network audit on results and detail pages | F11: NOT STARTED | G11: OBSERVED FROM RESEARCH
A12: Requests to first render | B12: How many separate network calls are needed before the page is usable. | C12: <= 25 | D12: > 40 | E12: Lighthouse network panel audit | F12: NOT STARTED | G12: OBSERVED FROM RESEARCH
A13: Search API latency (p95) | B13: How long the slowest 5% of searches take on the server. | C13: <= 300 ms | D13: > 600 ms | E13: Application performance monitoring at realistic data volume | F13: NOT STARTED | G13: OBSERVED FROM RESEARCH
A14: Typeahead latency (p95) | B14: How long autocomplete suggestions take to appear. | C14: <= 120 ms | D14: > 250 ms | E14: APM; must be measured against the dedicated suggest table | F14: NOT STARTED | G14: OBSERVED FROM RESEARCH
A15: Filter/sort error rate | B15: How often a filter or sort action fails. | C15: < 0.1 % | D15: > 0.5 % | E15: Error monitoring with a dedicated alert on these actions | F15: NOT STARTED | G15: OBSERVED FROM RESEARCH
A16: Test conditions | B16: The device and network profile all budgets are measured on. | C16: Throttled mid-range Android, simulated 4G | D16: Developer laptop on office wifi | E16: Configure Lighthouse and device testing to this profile | F16: NOT STARTED | G16: OBSERVED FROM RESEARCH

Sheet DEVOPS & DEPLOYMENT
A1: DEVOPS & DEPLOYMENT — running the system safely
A2: The backup RESTORE DRILL is the item most often assumed and never verified. An untested backup is not a backup.
A4: Area | B4: Item | C4: What To Do | D4: Why It Matters | E4: Phase | F4: Status | G4: Source
A5: Repository | B5: Create the repository | C5: Set up Git hosting with a README, licence and .gitignore. | D5: Single source of truth for code and history. | E5: Phase 1 | F5: NOT STARTED | G5: PROPOSED
A6: Repository | B6: Protect the main branch | C6: Require pull requests and passing checks before merge. | D6: Prevents broken code reaching production. | E6: Phase 1 | F6: NOT STARTED | G6: PROPOSED
A7: Repository | B7: CODEOWNERS | C7: Define who reviews which parts of the codebase. | D7: Useful the moment more than one person contributes. | E7: Phase 1 | F7: NOT STARTED | G7: PROPOSED
A8: Branch strategy | B8: Define branching rules | C8: Short-lived feature branches merged into main via pull request. | D8: Long-lived branches cause painful merges. | E8: Phase 1 | F8: NOT STARTED | G8: PROPOSED
A9: Branch strategy | B9: Commit conventions | C9: Adopt a consistent commit message format. | D9: Makes history readable and enables automated changelogs. | E9: Phase 1 | F9: NOT STARTED | G9: PROPOSED
A10: Environment variables | B10: Document every variable | C10: Maintain a .env.example listing every variable with a description. | D10: New environments are otherwise impossible to reproduce. | E10: Phase 1 | F10: NOT STARTED | G10: PROPOSED
A11: Environment variables | B11: Never commit real values | C11: Keep actual secrets out of the repository entirely. | D11: Secrets in Git history are extremely hard to remove. | E11: Phase 1 | F11: NOT STARTED | G11: OBSERVED FROM RESEARCH
A12: Environments | B12: Development environment | C12: Local setup running with one command via Docker Compose. | D12: Everyone develops against identical dependency versions. | E12: Phase 1 | F12: NOT STARTED | G12: PROPOSED
A13: Environments | B13: Staging environment | C13: A production-like environment with separate data. | D13: Never test against production data. | E13: Phase 19 | F13: NOT STARTED | G13: PROPOSED
A14: Environments | B14: Production environment | C14: The live environment, isolated from all others. | D14: Isolation prevents accidental data loss. | E14: Phase 19 | F14: NOT STARTED | G14: PROPOSED
A15: CI/CD | B15: Continuous integration | C15: Run lint, typecheck and tests on every pull request. | D15: Catches problems before merge, while they are cheap. | E15: Phase 1 | F15: NOT STARTED | G15: PROPOSED
... A54: Cost | B54: Cost monitoring and alerts | C54: Set budget alerts on cloud spend. | D54: Cloud bills surprise people, especially with image traffic. | E54: Phase 19 | F54: NOT STARTED | G54: PROPOSED

Sheet THIRD-PARTY SERVICES
A1: THIRD-PARTY SERVICES — what you must buy or sign up for
A2: Do NOT sign up for everything at once. Only the MVP rows are needed for launch. Note that DLT registration for Indian SMS has a lead time — start that early.
A4: Service | B4: Purpose | C4: MVP/Future | D4: Why Needed | E4: Alternative | F4: Estimated Cost | G4: Integration Phase | H4: Status | I4: Source
A5: SMS / OTP provider | B5: Deliver one-time codes and lead alerts by SMS. | C5: MVP | D5: OTP is the primary login method and the gate on contact reveal. Nothing works without it. | E5: MSG91, Twilio, AWS SNS, Gupshup | F5: Per-message; budget for OTP volume plus abuse margin. DLT registration required in India. | G5: Phase 5 | H5: NOT STARTED | I5: DECISION REQUIRED
A6: Email provider | B6: Transactional email: verification, lead alerts, notifications. | C6: MVP | D6: Secondary notification channel and account recovery. | E6: Resend, AWS SES, Postmark, SendGrid | F6: Low at launch volume; usually per-thousand emails. | G6: Phase 10 | H6: NOT STARTED | I6: DECISION REQUIRED
A7: Object storage | B7: Store listing photos and documents. | C7: MVP | D7: Images cannot live in the database; you need durable blob storage. | E7: AWS S3, Cloudflare R2, Google Cloud Storage | F7: Storage plus egress. R2 has no egress fee — relevant for an image-heavy product. | G7: Phase 4 | H7: NOT STARTED | I7: OBSERVED FROM RESEARCH
A8: CDN | B8: Serve assets and cache HTML at the edge. | C8: MVP | D8: The single cheapest performance improvement available. | E8: Cloudflare, Fastly, AWS CloudFront | F8: Free tier often sufficient at launch. | G8: Phase 19 | H8: NOT STARTED | I8: OBSERVED FROM RESEARCH
A9: Maps / geocoding | B9: Show property locations; geocode addresses. | C9: MVP (static map only) | D9: Location is the primary decision factor on the detail page. | E9: MapLibre + MapTiler/Protomaps, Google Maps, Mapbox | F9: MapLibre with open tiles can be near-free; Google bills per load and grows fast. | G9: Phase 6 | H9: NOT STARTED | I9: DECISION REQUIRED
A10: Error monitoring | B10: Capture and alert on application errors. | C10: MVP | D10: You cannot fix errors you never hear about. | E10: Sentry, Rollbar, Bugsnag | F10: Free tier usually sufficient at launch. | G10: Phase 15 | H10: NOT STARTED | I10: OBSERVED FROM RESEARCH
A11: Web analytics | B11: Understand traffic sources and page performance. | C11: MVP | D11: Tells you which acquisition channels actually work. | E11: GA4, Plausible, Fathom, PostHog | F11: Free to low. | G11: Phase 15 | H11: NOT STARTED | I11: DECISION REQUIRED
A12: Event analytics / product analytics | B12: Own the lead funnel data end to end. | C12: MVP | D12: The lead funnel is the business; owning this data is non-negotiable. | E12: PostHog (self-hosted or cloud), own pipeline to a warehouse | F12: Self-hosting trades money for operational effort. | G12: Phase 15 | H12: NOT STARTED | I12: OBSERVED FROM RESEARCH
A13: Hosting — frontend | B13: Run the server-rendered web application. | C13: MVP | D13: Required to serve the site. | E13: Vercel, Netlify, self-managed containers | F13: Scales with traffic; watch bandwidth on image-heavy pages. | G13: Phase 19 | H13: NOT STARTED | I13: DECISION REQUIRED
A14: Hosting — backend & database | B14: Run the API, workers and database. | C14: MVP | D14: Required to serve the site. | E14: AWS, GCP, Railway, Render, Fly.io, DigitalOcean | F14: Managed database is worth the premium at this stage. | G14: Phase 19 | H14: NOT STARTED | I14: DECISION REQUIRED
A15: Uptime monitoring | B15: External checks that the site is up. | C15: MVP | D15: Tells you about outages before users do. | E15: BetterStack, UptimeRobot, Pingdom | F15: Free tier usually sufficient. | G15: Phase 19 | H15: NOT STARTED | I15: OBSERVED FROM RESEARCH
... A24: Secrets manager | B24: Store credentials securely. | C24: MVP | D24: Environment files on servers get copied and leaked. | E24: AWS Secrets Manager, Doppler, Infisical, 1Password | F24: Low. | G24: Phase 17 | H24: NOT STARTED | I24: OBSERVED FROM RESEARCH

Sheet MONETIZATION ROADMAP
A1: MONETIZATION ROADMAP — how the product makes money, and when
A2: Nothing is charged at launch, deliberately. The research's central finding is that the monetisable event is the contact reveal: instrument it from day one, charge for it later.
A4: Item | B4: Type | C4: MVP/Future | D4: Description | E4: Rationale | F4: Dependencies | G4: Target Release | H4: Status | I4: Source
A5: Free listings for everyone | B5: Free | C5: MVP | D5: All sellers can list at no cost during the first phase. | E5: You cannot charge before proving liquidity and lead quality. Charging on thin supply kills marketplaces. | F5: Phase 7 | G5: MVP | H5: NOT STARTED | I5: OBSERVED FROM RESEARCH
A6: Free listing quota | B6: Quota | C6: MVP | D6: Limit the number of free active listings per account. | E6: Creates the scarcity that later plans relieve. Build the accounting even while everything is free. | F6: Phase 7 | G6: MVP | H6: NOT STARTED | I6: OBSERVED FROM RESEARCH
A7: Quota ledger (append-only) | B7: Infrastructure | C7: MVP | D7: Record every quota consumption as an immutable ledger entry. | E7: Quota disputes are common; an append-only ledger is the only defensible answer. | F7: Phase 7 | G7: MVP | H7: NOT STARTED | I7: OBSERVED FROM RESEARCH
A8: Lead instrumentation | B8: Infrastructure | C8: MVP | D8: Record every enquiry and contact reveal as a first-class object. | E8: You cannot price what you cannot measure. This is the monetisable event. | F8: Phase 10 | G8: MVP | H8: NOT STARTED | I8: OBSERVED FROM RESEARCH
A9: Lead quality measurement | B9: Analytics | C9: MVP | D9: Track which leads sellers mark as qualified or closed. | E9: Lead quality — not volume — is what sellers will pay for. | F9: Phase 10, 15 | G9: MVP | H9: NOT STARTED | I9: OBSERVED FROM RESEARCH
A10: Buyer side stays free | B10: Policy | C10: MVP | D10: Buyers and tenants never pay. | E10: Standard for the category; charging buyers destroys the demand side that sellers are paying to reach. | F10: — | G10: Permanent | H10: NOT STARTED | I10: OBSERVED FROM RESEARCH
A11: Owner paid plan | B11: Subscription | C11: FUTURE | D11: More listings, longer duration, verified badge, featured days, analytics. | E11: The individual-owner cohort is underserved by sales-assisted enterprise pricing. | F11: Payments | G11: v1.3 | H11: NOT STARTED | I11: OBSERVED FROM RESEARCH
A12: Agent starter plan | B12: Subscription | C12: FUTURE | D12: Listing allowance, lead inbox, bulk upload, public profile. | E12: Agents are the recurring-revenue cohort. | F12: Payments, agent tools | G12: v1.3 | H12: NOT STARTED | I12: OBSERVED FROM RESEARCH
A13: Agent pro plan | B13: Subscription | C13: FUTURE | D13: Higher allowances, featured credits, priority placement, CRM export. | E13: Upgrade path for high-volume agents. | F13: Agent starter | G13: v1.4 | H13: NOT STARTED | I13: OBSERVED FROM RESEARCH
A14: Builder package | B14: Subscription | C14: FUTURE | D14: Project microsite, unlimited configurations, brand placement, campaign reporting. | E14: Builders have the largest marketing budgets in this category. | F14: Projects module | G14: v1.5 | H14: NOT STARTED | I14: OBSERVED FROM RESEARCH
A15: Payments and GST invoicing | B15: Infrastructure | C15: FUTURE | D15: Take payment and issue compliant invoices. | E15: Required before any money can be collected in India. | F15: Payment gateway | G15: v1.3 | H15: NOT STARTED | I15: OBSERVED FROM RESEARCH
... A25: Never sell undisclosed ranking | B25: Policy | C25: FUTURE | D25: All paid placement is labelled and bounded. | E25: Trust is the only durable advantage against an incumbent with more inventory. | F25: — | G25: Permanent | H25: NOT STARTED | I25: OBSERVED FROM RESEARCH

Sheet LAUNCH CHECKLIST
A1: LAUNCH CHECKLIST — the final gate before going live
A2: Every item must be DONE or consciously DEFERRED. Work through this top to bottom in Phase 20. If an item is not true, you are not ready.
A4: Category | B4: Item | C4: What Must Be True | D4: Status | E4: Owner | F4: Notes
A5: Product | B5: MVP scope complete | C5: Every item marked MVP in the MVP CHECKLIST is DONE or consciously DEFERRED. | D5: NOT STARTED | E5: UNASSIGNED
A6: Product | B6: Success metrics defined | C6: Targets agreed and measurable in the analytics dashboard. | D6: NOT STARTED | E6: UNASSIGNED
A7: Product | B7: Launch cities confirmed | C7: Cities are named, and the gazetteer covers them fully. | D7: NOT STARTED | E7: UNASSIGNED
A8: Product | B8: Minimum inventory reached | C8: Enough active listings exist that search is useful in every launch city. | D8: NOT STARTED | E8: UNASSIGNED | F8: Research proposes 2,000+ across 3 cities.
A9: UI/UX | B9: All MVP screens built | C9: Every page marked MVP in WEBSITE PAGES exists and is reachable. | D9: NOT STARTED | E9: UNASSIGNED
A10: UI/UX | B10: Empty, loading and error states | C10: Every list and form has all three states designed and implemented. | D10: NOT STARTED | E10: UNASSIGNED
A11: UI/UX | B11: Mobile responsiveness verified | C11: Tested at 390, 412, 768, 1024 and 1280px with no layout defects. | D11: NOT STARTED | E11: UNASSIGNED
A12: UI/UX | B12: Accessibility pass | C12: Keyboard navigation works; focus visible; contrast meets AA. | D12: NOT STARTED | E12: UNASSIGNED
A13: UI/UX | B13: Original branding confirmed | C13: No competitor branding, wording, imagery or visual identity anywhere. | D13: NOT STARTED | E13: UNASSIGNED | F13: Legal requirement, not a preference.
A14: Database | B14: Schema finalised for MVP | C14: All MVP tables exist with indexes and constraints. | D14: NOT STARTED | E14: UNASSIGNED
A15: Database | B15: Migrations tested | C15: Migrations run forward and roll back cleanly on a copy of production. | D15: NOT STARTED | E15: UNASSIGNED
A16: Database | B16: Seed and reference data loaded | C16: Property types, amenities and the gazetteer are populated. | D16: NOT STARTED | E16: UNASSIGNED
A17: Database | B17: Backups running and restored once | C17: A real restore has been performed into a clean environment. | D17: NOT STARTED | E17: UNASSIGNED | F17: Do not accept an untested backup.
A18: Backend | B18: All MVP APIs implemented | C18: Every API marked MVP responds correctly including error cases. | D18: NOT STARTED | E18: UNASSIGNED
A19: Backend | B19: Health endpoint live | C19: Monitoring can confirm application and dependency health. | D19: NOT STARTED | E19: UNASSIGNED
A20: Backend | B20: Background workers running | C20: Image processing, moderation, notifications and indexing all process jobs. | D20: NOT STARTED | E20: UNASSIGNED
A21: Backend | B21: Rate limits active | C21: Search, OTP, reveal and upload endpoints are rate-limited. | D21: NOT STARTED | E21: UNASSIGNED
A22: Frontend | B22: Server-side rendering verified | C22: Page source contains listing content without JavaScript enabled. | D22: NOT STARTED | E22: UNASSIGNED
A23: Frontend | B23: No console errors | C23: No errors in the browser console on any core journey. | D23: NOT STARTED | E23: UNASSIGNED
A24: Frontend | B24: Images optimised | C24: Modern formats, responsive sizes, correct lazy loading, reserved space. | D24: NOT STARTED | E24: UNASSIGNED
A25: Authentication | B25: OTP delivery reliable | C25: Codes arrive within seconds on all major Indian networks. | D25: NOT STARTED | E25: UNASSIGNED | F25: Verify DLT template approval is complete.
A26: Authentication | B26: Session handling correct | C26: Login persists; refresh works; logout revokes. | D26: NOT STARTED | E26: UNASSIGNED
A27: Authentication | B27: Role permissions enforced | C27: Cross-role access attempts fail, verified by automated tests. | D27: NOT STARTED | E27: UNASSIGNED
A28: Search | B28: All filters correct | C28: Every filter returns exactly the right results against seeded data. | D28: NOT STARTED | E28: UNASSIGNED
A29: Search | B29: Facet counts correct | C29: Counts verified against manual expectation. | D29: NOT STARTED | E29: UNASSIGNED
A30: Search | B30: Filter state never lost | C30: No filter or sort action loses state, even when the API errors. | D30: NOT STARTED | E30: UNASSIGNED | F30: The single most important quality bar for this product.
A31: Search | B31: Zero-result recovery works | C31: Relaxation ladder triggers and explains itself. | D31: NOT STARTED | E31: UNASSIGNED
A32: Search | B32: Search latency within budget | C32: p95 within the PERFORMANCE sheet target at realistic volume. | D32: NOT STARTED | E32: UNASSIGNED
A33: Property posting | B33: Wizard completes on mobile | C33: Five external users completed posting unaided; median under 8 minutes. | D33: NOT STARTED | E33: UNASSIGNED
A34: Property posting | B34: Autosave verified | C34: Refreshing mid-form loses nothing. | D34: NOT STARTED | E34: UNASSIGNED
A35: Property posting | B35: Photo upload reliable | C35: Works on a slow mobile connection with retry on failure. | D35: NOT STARTED | E35: UNASSIGNED
A36: Property posting | B36: Quota enforced | C36: Over-quota publishing is blocked with a clear message. | D36: NOT STARTED | E36: UNASSIGNED
A37: Leads | B37: Enquiry delivered end to end | C37: Enquiry reaches the seller inbox and notifies them. | D37: NOT STARTED | E37: UNASSIGNED
A38: Leads | B38: Contact reveal records before revealing | C38: Inquiry is written before the number is displayed. | D38: NOT STARTED | E38: UNASSIGNED
A39: Leads | B39: Duplicate reveals deduplicated | C39: Repeat reveal creates no second billable lead. | D39: NOT STARTED | E39: UNASSIGNED
A40: Leads | B40: Contact details not leaked in API | C40: Raw network responses contain no seller phone number before reveal. | D40: NOT STARTED | E40: UNASSIGNED
A41: Admin | B41: Moderation queue operational | C41: Listings can be approved and rejected with reasons. | D41: NOT STARTED | E41: UNASSIGNED
A42: Admin | B42: Reports handled | C42: Reporting works and reports reach the queue with an SLA timer. | D42: NOT STARTED | E42: UNASSIGNED
A43: Admin | B43: Audit log recording | C43: Every admin action writes an immutable entry. | D43: NOT STARTED | E43: UNASSIGNED
A44: Admin | B44: Staff trained | C44: Whoever moderates knows the policy and the tools. | D44: NOT STARTED | E44: UNASSIGNED | F44: Often forgotten; moderation quality depends on it.
A45: SEO | B45: URLs final | C45: No indexable URL will change after launch. | D45: NOT STARTED | E45: UNASSIGNED | F45: Changing URLs post-indexing costs ranking.
A46: SEO | B46: Canonicals correct | C46: Every page declares the intended canonical URL. | D46: NOT STARTED | E46: UNASSIGNED
A47: SEO | B47: Indexation rules applied | C47: App surface noindex; thin pages noindex; allowlist enforced. | D47: NOT STARTED | E47: UNASSIGNED
A48: SEO | B48: Sitemaps live and submitted | C48: Sitemap index generated, valid and submitted to Search Console. | D48: NOT STARTED | E48: UNASSIGNED
A49: SEO | B49: robots.txt correct | C49: Nothing in the sitemap is disallowed. | D49: NOT STARTED | E49: UNASSIGNED
A50: SEO | B50: Structured data valid | C50: JSON-LD validates on every page type. | D50: NOT STARTED | E50: UNASSIGNED
A51: SEO | B51: Search Console verified | C51: Property verified and coverage monitoring in place. | D51: NOT STARTED | E51: UNASSIGNED
A52: Security | B52: Independent security review passed | C52: All critical and high findings resolved. | D52: NOT STARTED | E52: UNASSIGNED
A53: Security | B53: No secrets in the repository | C53: Git history verified clean. | D53: NOT STARTED | E53: UNASSIGNED
A54: Security | B54: HTTPS enforced with HSTS | C54: HTTP redirects; certificate auto-renews. | D54: NOT STARTED | E54: UNASSIGNED
A55: Security | B55: Security headers set | C55: CSP and related headers verified by an external scanner. | D55: NOT STARTED | E55: UNASSIGNED
A56: Security | B56: PII protected | C56: Personal data encrypted at rest; lead access logged. | D56: NOT STARTED | E56: UNASSIGNED
A57: Performance | B57: All budgets met | C57: Every target in the PERFORMANCE sheet is green on five representative routes. | D57: NOT STARTED | E57: UNASSIGNED
... A64: Legal | B64: Privacy policy published | C64: Describes data collected, retention and user rights. | D64: NOT STARTED | E64: UNASSIGNED
A65: Legal | B65: Verification scope disclaimer | C65: States exactly what a verified badge does and does not prove. | D65: NOT STARTED | E65: UNASSIGNED | F65: Copy the honesty of this scoping — it is legally protective.
A66: Legal | B66: Data-protection compliance | C66: Consent capture, retention limits and deletion flow all working. | D66: NOT STARTED | E66: UNASSIGNED
A67: Legal | B67: Contact and grievance channel | C67: A monitored support address and complaint process exist. | D67: NOT STARTED | E67: UNASSIGNED
A68: Domain | B68: Domain live | C68: Domain resolves, HTTPS works, www and apex behave consistently. | D68: NOT STARTED | E68: UNASSIGNED
A69: Domain | B69: Email deliverability | C69: SPF, DKIM and DMARC configured so transactional email is not spam-filed. | D69: NOT STARTED | E69: UNASSIGNED
A70: Deployment | B70: Production deploy tested | C70: A full deploy has been performed successfully. | D70: NOT STARTED | E70: UNASSIGNED
A71: Deployment | B71: Rollback tested | C71: A rollback has been performed on staging. | D71: NOT STARTED | E71: UNASSIGNED
A72: Deployment | B72: Monitoring and alerting live | C72: A simulated outage produced an alert to a real person. | D72: NOT STARTED | E72: UNASSIGNED
A73: Deployment | B73: Disaster recovery plan written | C73: RTO and RPO defined with named steps and owners. | D73: NOT STARTED | E73: UNASSIGNED
A74: Testing | B74: Full test suite green | C74: All automated tests pass on the release build. | D74: NOT STARTED | E74: UNASSIGNED
A75: Testing | B75: User acceptance testing complete | C75: External users completed both posting and search journeys. | D75: NOT STARTED | E75: UNASSIGNED
A76: Testing | B76: Production smoke tests pass | C76: Post, search, contact and OTP verified on the live site. | D76: NOT STARTED | E76: UNASSIGNED
A77: Testing | B77: Cross-browser verified | C77: No blocking defect in Chrome, Safari, Firefox or Edge. | D77: NOT STARTED | E77: UNASSIGNED
... A80: Launch ops | B80: Rollback decision criteria agreed | C80: You know in advance what would make you roll back. | D80: NOT STARTED | E80: UNASSIGNED

Sheet POST-LAUNCH ROADMAP
A1: POST-LAUNCH ROADMAP — what comes after launch
A2: Grouped into releases. Nothing here is invented: every item is either deferred from the MVP scope or recommended by the research document.
A4: Release | B4: Item | C4: Category | D4: Description | E4: Why | F4: Priority | G4: Status | H4: Source
A5: Immediate (weeks 1–4) | B5: Triage and fix critical defects | C5: Stability | D5: Fix anything blocking a core journey. | E5: Broken core journeys destroy early word of mouth permanently. | F5: CRITICAL | G5: NOT STARTED | H5: OBSERVED FROM RESEARCH
A6: Immediate (weeks 1–4) | B6: Measure against launch targets | C6: Analytics | D6: Compare actual funnel numbers to the agreed targets. | E6: Tells you whether to optimise or change direction. | F6: CRITICAL | G6: NOT STARTED | H6: OBSERVED FROM RESEARCH
A7: Immediate (weeks 1–4) | B7: Fix the weakest funnel step | C7: Conversion | D7: Focus entirely on whichever step is furthest from target. | E7: Focused effort beats broad tinkering. | F7: CRITICAL | G7: NOT STARTED | H7: OBSERVED FROM RESEARCH
A8: Immediate (weeks 1–4) | B8: Review SEO indexation | C8: SEO | D8: Check what actually got indexed and fix crawl errors. | E8: Indexation problems are invisible unless checked. | F8: HIGH | G8: NOT STARTED | H8: OBSERVED FROM RESEARCH
A9: Immediate (weeks 1–4) | B9: Tune duplicate detection | C9: Quality | D9: Adjust thresholds using real listing data. | E9: Our stated differentiator; needs live data to calibrate. | F9: HIGH | G9: NOT STARTED | H9: OBSERVED FROM RESEARCH
A10: Immediate (weeks 1–4) | B10: Reduce moderation backlog | C10: Operations | D10: Tune auto-approval so human review stays manageable. | E10: Slow review frustrates sellers and slows supply growth. | F10: HIGH | G10: NOT STARTED | H10: OBSERVED FROM RESEARCH
A11: v1.1 — Discovery | B11: Interactive map search | C11: Search | D11: Bounding-box search with clustered markers and list toggle. | E11: Highly requested in this category; deferred from MVP for cost and complexity. | F11: HIGH | G11: NOT STARTED | H11: OBSERVED FROM RESEARCH
A12: v1.1 — Discovery | B12: Saved searches with alerts | C12: Retention | D12: Let buyers save a search and be notified of new matches. | E12: The single best retention mechanism for a months-long decision. | F12: HIGH | G12: NOT STARTED | H12: OBSERVED FROM RESEARCH
A13: v1.1 — Discovery | B13: Comparison view | C13: Buyer tools | D13: Side-by-side comparison with normalised area basis and price per unit. | E13: Buyers build these spreadsheets manually today — a real differentiator. | F13: MEDIUM | G13: NOT STARTED | H13: OBSERVED FROM RESEARCH
A14: v1.1 — Discovery | B14: Recent searches sync | C14: Retention | D14: Persist recent searches across devices for logged-in users. | E14: Property search spans weeks and multiple devices. | F14: MEDIUM | G14: NOT STARTED | H14: OBSERVED FROM RESEARCH
A15: v1.1 — Discovery | B15: WhatsApp contact option | C15: Leads | D15: Offer WhatsApp as a contact channel. | E15: Dominant communication channel in the Indian market. | F15: HIGH | G15: NOT STARTED | H15: PROPOSED
... A54: Long-term | B54: Microservice extraction | C54: Platform | D54: Split modules into services only if team size and load require it. | E54: A solution to an organisational problem you do not yet have. | F54: LOW | G54: NOT STARTED | H54: OBSERVED FROM RESEARCH

Sheet DECISIONS LOG
A1: DECISIONS LOG — questions only YOU can answer
A2: THE MOST IMPORTANT SHEET FOR YOU. Nothing is decided automatically. Review weekly: write your answer in 'Final Decision', set the date, and change Decision Status to DECIDED.
A4: Decision ID | B4: Decision | C4: Options | D4: Recommended / Proposed Direction | E4: Reason | F4: Impact | G4: Decision Status | H4: Final Decision | I4: Date
A5: D-01 | B5: Frontend framework and language | C5: (a) Next.js + React + TypeScript (b) Remix (c) Nuxt/Vue (d) Plain React SPA | D5: Next.js (App Router) + React + TypeScript | E5: Server-side rendering is a hard requirement for the SEO architecture. Option (d) cannot deliver it without a rewrite. Research §22. | F5: Very high — affects every frontend task, hiring, and whether SEO works at all. | G5: OPEN — DECISION REQUIRED
A6: D-02 | B6: Backend framework and architecture style | C6: (a) NestJS modular monolith (TypeScript) (b) Spring Boot (Java) (c) Django (Python) (d) Microservices from day one | D6: NestJS modular monolith | E6: Same language as the frontend means shared types and one skill set for a small team. Microservices solve an organisational problem you do not have yet. Research §21.1, §22. | F6: Very high — affects hiring, libraries, deployment and delivery speed. | G6: OPEN — DECISION REQUIRED
A7: D-03 | B7: Primary database | C7: (a) PostgreSQL + PostGIS (b) MySQL (c) MongoDB | D7: PostgreSQL 16 + PostGIS | E7: One engine covers relational data, geospatial search, full-text search and JSON for the entire first phase. Research §22. | F7: Very high — the data model constrains everything built on it. | G7: OPEN — DECISION REQUIRED
A8: D-04 | B8: Search engine approach | C8: (a) PostgreSQL only, migrate later (b) OpenSearch/Elasticsearch from day one (c) Hosted search (Algolia/Typesense) | D8: PostgreSQL first; add OpenSearch at a measured trigger | E8: Running a search cluster before there is data to justify it adds operational burden for no benefit. Set an explicit migration trigger (listing count or facet latency). Research §13.3. | F8: High — but reversible if the index is kept as a derived, rebuildable projection. | G8: OPEN — DECISION REQUIRED
A9: D-05 | B9: Image and object storage | C9: (a) Cloudflare R2 (b) AWS S3 (c) Google Cloud Storage | D9: R2 or S3, decided together with hosting (D-07) | E9: This is an image-heavy product, so egress cost matters. R2 charges no egress; S3 does. Compare against where the rest of the stack lives. | F9: Medium — migration is possible but tedious once there are many files. | G9: OPEN — DECISION REQUIRED
A10: D-06 | B10: Maps and geocoding provider | C10: (a) MapLibre + open vector tiles (b) Google Maps Platform (c) Mapbox | D10: Decide with a cost model before Phase 6 | E10: MapLibre avoids per-load billing; Google has better Indian place data and autocomplete. This is a genuine trade-off between cost and data quality. Research §22. | F10: Medium-high — affects cost at scale and the quality of location search. | G10: OPEN — DECISION REQUIRED
A11: D-07 | B11: Hosting and cloud provider | C11: (a) Vercel (frontend) + managed containers (backend) (b) Single cloud — AWS/GCP (c) Simplified platform — Railway/Render/Fly | D11: Start managed; avoid Kubernetes until the team needs it | E11: Operational simplicity is worth more than theoretical flexibility at launch. Research §22 explicitly defers Kubernetes. | F11: High — affects cost, deployment complexity and every DevOps task. | G11: OPEN — DECISION REQUIRED
A12: D-08 | B12: Authentication and session strategy | C12: (a) Own OTP flow + JWT access with rotating refresh (b) Managed auth provider (c) Session cookies only | D12: Own OTP flow with rotating refresh tokens | E12: Authentication is core to this product (roles, quotas, contact-reveal gating), and OTP-first is the right pattern for India. Research §22. | F12: High — security-critical and hard to change after launch. | G12: OPEN — DECISION REQUIRED
A13: D-09 | B13: OTP / SMS provider | C13: (a) MSG91 (b) Twilio (c) AWS SNS (d) Gupshup | D13: Choose an India-focused provider and start DLT registration EARLY | E13: DLT template registration is legally required in India and has a lead time that can delay launch. Decide before Phase 5. | F13: High — nothing in the product works without reliable OTP delivery. | G13: OPEN — DECISION REQUIRED
A14: D-10 | B14: Analytics stack | C14: (a) PostHog (events + flags + replay) (b) Own pipeline to a warehouse + GA4 (c) GA4 only | D14: PostHog or an owned pipeline; GA4 alone is not enough | E14: The lead funnel is the business. GA4 cannot answer lead-level questions. Research §22 calls owning event data non-negotiable. | F14: Medium-high — retrofitting event tracking loses all historical data. | G14: OPEN — DECISION REQUIRED
A15: D-11 | B15: MVP launch cities | C15: (a) One city (b) Three cities (c) One metro plus its satellite towns | D15: Research proposes three cities — YOU MUST NAME THEM | E15: Cities determine the gazetteer work, the supply plan and the inventory target. This is a business decision only you can make. Research §24. | F15: Very high — determines scope, effort and whether launch inventory is achievable. | G15: OPEN — DECISION REQUIRED
A16: D-12 | B16: Property categories in MVP | C16: (a) Residential Buy + Rent only (b) Add Commercial (c) Add PG (d) Add Plots | D16: Residential Buy + Rent only | E16: Each additional category is a full field schema, filter set and landing-page family. Research §24 defers all three. | F16: High — each category added roughly extends the posting and search work. | G16: OPEN — DECISION REQUIRED
... A29: D-25 | B29: ORM / database access layer | C29: (a) Prisma (b) Drizzle (c) TypeORM (d) Raw SQL with a query builder | D29: Prisma, dropping to raw SQL for hot search paths | E29: Type-safe with good migrations, but search queries usually need hand-written SQL anyway. Research §22. | F29: Medium — changing it later is a large refactor. | G29: OPEN — DECISION REQUIRED

Sheet GLOSSARY
A1: GLOSSARY — every technical term in plain English
A2: If a word anywhere in this workbook is unfamiliar, look here first. No prior technical knowledge is assumed.
A4: Term | B4: Plain-English Meaning | C4: Why It Matters For This Project | D4: Where You Will See It
A5: API | B5: A way for one program to ask another program for data or to do something. Like a waiter carrying orders between you and the kitchen. | C5: Your website (frontend) talks to your server (backend) through APIs. Every button that loads data calls one. | D5: API CHECKLIST sheet; Phases 4–12
A6: Frontend | B6: Everything the user sees and clicks in their browser or app. | C6: This is where your design system, pages and interactions live. | D6: UI/UX CHECKLIST; WEBSITE PAGES; Phase 3
A7: Backend | B7: The part that runs on your servers: business rules, database access, security. Users never see it directly. | C7: Where listings are stored, leads are recorded and permissions are enforced. | D7: Phases 4–13; API CHECKLIST
A8: Database | B8: An organised store of your data — users, listings, leads — that can be searched and updated reliably. | C8: The single most important technical asset you own. Everything else can be rebuilt. | D8: DATABASE sheet; Phase 4
A9: PostgreSQL | B9: A specific, free, very reliable database system. Often shortened to 'Postgres'. | C9: Recommended as your main database because it handles text search, location search and normal data in one system. | D9: DECISIONS LOG D-03; Phase 4
A10: PostGIS | B10: An add-on for PostgreSQL that understands maps and locations — distances, areas, 'what is inside this boundary'. | C10: Property search is fundamentally about location. This is what makes 'within 5 km' work. | D10: DATABASE sheet; Phase 6
A11: Redis | B11: A very fast temporary store kept in memory. Used to remember answers so you do not recalculate them. | C11: Makes filter counts and autocomplete fast, and enforces rate limits. | D11: Phase 4; PERFORMANCE
A12: OpenSearch / Elasticsearch | B12: Specialised software built purely for searching and filtering large amounts of data quickly. | C12: You will NOT use this at first. It is deliberately deferred until PostgreSQL stops keeping up. | D12: DECISIONS LOG D-04; POST-LAUNCH v2.0
A13: CDN (Content Delivery Network) | B13: A network of servers worldwide that keeps copies of your images and files close to users. | C13: Images are the heaviest part of a property site. A CDN is the cheapest speed improvement available. | D13: DEVOPS; PERFORMANCE
A14: SSR (Server-Side Rendering) | B14: The server builds the complete page and sends finished HTML to the browser. | C14: Essential for SEO. Search engines see your listings properly, and pages appear faster. | D14: Phase 2; SEO CHECKLIST
A15: SSG (Static Site Generation) | B15: Pages are built once in advance and served as ready-made files. | C15: Extremely fast, but only suitable for pages whose content rarely changes. | D15: Phase 2; WEBSITE PAGES
... A57: Technical debt | B57: Shortcuts taken now that cost more to fix later. | C57: Performance and URL structure are the two kinds of debt this project must not take on. | D57: Phase 14, 16
